{
	"content": [
		{
			"title": "Voici le top cinq des sports dont la pratique rallonge votre esp\u00e9rance de vie - Ouest-France",
			"link": "https://www.ouest-france.fr/leditiondusoir/2025-06-12/voici-le-top-cinq-des-sports-dont-la-pratique-rallonge-votre-esperance-de-vie-0ea6774f-a899-43d1-b53b-34ad9efb4484",
			"pubDate": "Thu, 12 Jun 2025 16:32:12 GMT",
			"image": "",
			"logo": "https://picsum.photos/32/32?grayscale",
			"site_name": "",
			"url": "",
			"description": ""
		},
		{
			"title": "[Podcasts] Les Grandes Gueules du Sport du 15 juin - 10h/11h - RMC Sport",
			"link": "https://rmcsport.bfmtv.com/replay-emissions/les-grandes-gueules-du-sport/les-grandes-gueules-du-sport-du-15-juin-10h-11h_EN-202506150155.html",
			"pubDate": "Sun, 15 Jun 2025 09:04:28 GMT",
			"image": "https://images.bfmtv.com/ye2HwDXFAxwdW6zLhwUVS4twQBc=/0x0:12000x6280/1200x0/images/image_composition_EN-202506150155.jpg",
			"logo": "https://picsum.photos/32/32?grayscale",
			"site_name": "RMC Sport",
			"url": "https://rmcsport.bfmtv.com/replay-emissions/les-grandes-gueules-du-sport/les-grandes-gueules-du-sport-du-15-juin-10h-11h_EN-202506150155.html",
			"description": "Apr\u00e8s une premi\u00e8re demi-heure \u00e0 s'\u00e9chauffer, les Grandes Gueules montent au cr\u00e9neau : un face \u00e0 face toujours br\u00fblant dans le bras de Fer, la Punchline et pour finir, la rubrique que nos GG craignent : le d\u00e9bat cach\u00e9 ! C'est le programme de 10h00 \u00e0 11h00 dans les Grandes Gueules du Sport."
		},
		{
			"title": "Ved\u00e8ne. En mode sport au Parc Bardi - Le Dauphin\u00e9 Lib\u00e9r\u00e9",
			"link": "https://www.ledauphine.com/societe/2025/06/15/en-mode-sport-au-parc-bardi",
			"pubDate": "Sun, 15 Jun 2025 15:39:28 GMT",
			"image": "https://cdn-s-www.ledauphine.com/images/3C3AE26C-7287-4AD0-AAFF-4F7A0484D671/FB1200/photo-1750002474.jpg",
			"logo": "https://picsum.photos/32/32?grayscale",
			"site_name": "",
			"url": "https://www.ledauphine.com/societe/2025/06/15/en-mode-sport-au-parc-bardi",
			"description": "Ce mercredi, le parc Bardi s\u2019est transform\u00e9 en village olympique \u00e0 l\u2019occasion de l\u2019\u00e9v\u00e9nement Ved\u00e8ne en mode sport. Une belle journ\u00e9e d\u00e9di\u00e9e \u00e0 la ..."
		},
		{
			"title": "\u00c0 Royan, le 4e challenge national du SAR Futsal, vitrine d\u2019un sport spectaculaire - Sud Ouest",
			"link": "https://www.sudouest.fr/lieux/charente-maritime/royan/a-royan-le-4e-challenge-national-du-sar-futsal-vitrine-d-un-sport-spectaculaire-24865261.php",
			"pubDate": "Sun, 15 Jun 2025 16:22:39 GMT",
			"image": "https://media.sudouest.fr/24865261/1200x-1/img-5638.jpg",
			"logo": "https://picsum.photos/32/32?grayscale",
			"site_name": "SudOuest.fr",
			"url": "https://www.sudouest.fr/lieux/charente-maritime/royan/a-royan-le-4e-challenge-national-du-sar-futsal-vitrine-d-un-sport-spectaculaire-24865261.php",
			"description": "Parmi les 16 \u00e9quipes qui s\u2019affronteront les samedi\u00a021 et dimanche 22\u00a0juin \u00e0 l\u2019Espace Cordouan, le club royannais a invit\u00e9 une \u00e9quipe de D1 et une \u00e9quipe de D2"
		},
		{
			"title": "Sports. La r\u00e9daction d\u2019Ouest-France cherche des correspondants en Mayenne . Sport - - Le Mans.maville.com",
			"link": "https://lemans.maville.com/sport/detail_-sports.-la-redaction-d-ouest-france-cherche-des-correspondants-en-mayenne-_-6854812_actu.Htm",
			"pubDate": "Sun, 15 Jun 2025 16:55:00 GMT",
			"image": "https://maville.com/photosmvi/2025/06/15/P35292555D6854812G_crop_1080-600_.jpg",
			"logo": "https://picsum.photos/32/32?grayscale",
			"site_name": "",
			"url": "https://lemans.maville.com/sport/detail_-sports.-la-redaction-d-ouest-france-cherche-des-correspondants-en-mayenne-_-6854812_actu.Htm",
			"description": "Sport Le Mans Sports La r\u00e9daction dOuest-France cherche des correspondants en Mayenne - La... Le Mans"
		},
		{
			"title": "Sport en direct. Les r\u00e9sultats de ce dimanche en Lorraine et ailleurs... - Le Republicain Lorrain",
			"link": "https://www.republicain-lorrain.fr/sport/2025/06/15/les-resultats-de-ce-dimanche-en-lorraine-et-ailleurs",
			"pubDate": "Sun, 15 Jun 2025 15:16:24 GMT",
			"image": "https://cdn-s-www.republicain-lorrain.fr/images/FF139BDC-9317-4EAF-97FA-D193D6019172/FB1200/photo-1749991180.jpg",
			"logo": "https://picsum.photos/32/32?grayscale",
			"site_name": "",
			"url": "https://www.republicain-lorrain.fr/sport/2025/06/15/les-resultats-de-ce-dimanche-en-lorraine-et-ailleurs",
			"description": "Football (Barrage N3, coupes de Moselle), basket, handball, tennis... D\u00e9couvrez tous les r\u00e9sultats et classements du jour."
		},
		{
			"title": "Frouzins. Valentine Dupr\u00e9, une championne qui allie l\u2019art et le sport - ladepeche.fr",
			"link": "https://www.ladepeche.fr/2025/06/15/valentine-dupre-une-championne-qui-allie-lart-et-le-sport-12763011.php",
			"pubDate": "Sun, 15 Jun 2025 03:12:00 GMT",
			"image": "https://images.ladepeche.fr/api/v1/images/view/684e3b78277f58f9530838be/large/image.jpg?v=1",
			"logo": "https://picsum.photos/32/32?grayscale",
			"site_name": "ladepeche.fr",
			"url": "https://www.ladepeche.fr/2025/06/15/valentine-dupre-une-championne-qui-allie-lart-et-le-sport-12763011.php",
			"description": "Pour la deuxi\u00e8me ann\u00e9e cons\u00e9cutive, la jeune frouzinoise Valentine Dupr\u00e9 est championne de France de Taekwondo."
		},
		{
			"title": "Sport boules - Ligue M1. G\u00e9nelard s\u2019offre un r\u00e9cital \u00e0 domicile et remporte la 9e \u00e9tape - Le JSL",
			"link": "https://www.lejsl.com/sport/2025/06/14/genelard-s-offre-un-recital-a-domicile-et-remporte-la-9e-etape",
			"pubDate": "Sat, 14 Jun 2025 20:37:10 GMT",
			"image": "https://cdn-s-www.lejsl.com/images/6B8EFE99-1821-4E9D-B46F-8C7AB63F4B5D/FB1200/photo-1749933323.jpg",
			"logo": "https://picsum.photos/32/32?grayscale",
			"site_name": "",
			"url": "https://www.lejsl.com/sport/2025/06/14/genelard-s-offre-un-recital-a-domicile-et-remporte-la-9e-etape",
			"description": "Ce samedi, G\u00e9nelard a remport\u00e9 la 9e \u00e9tape de Ligue M1, organis\u00e9e \u00e0 la maison. Vainqueurs des quatre premiers du classement jusqu\u2019en demi-finales, ..."
		},
		{
			"title": "Sport-boules - Ligue M1. Le Bourguignon Anthony Percherancier ma\u00eetre sur ses jeux - Le Dauphin\u00e9 Lib\u00e9r\u00e9",
			"link": "https://www.ledauphine.com/sport/2025/06/15/le-bourguignon-percherancier-maitre-sur-ses-jeux",
			"pubDate": "Sun, 15 Jun 2025 19:22:43 GMT",
			"image": "https://cdn-s-www.ledauphine.com/images/09538538-D97F-4481-B7FD-9C628E568331/FB1200/photo-1750015045.jpg",
			"logo": "https://picsum.photos/32/32?grayscale",
			"site_name": "",
			"url": "https://www.ledauphine.com/sport/2025/06/15/le-bourguignon-percherancier-maitre-sur-ses-jeux",
			"description": "Anthony Percherancier (G\u00e9nelard) n\u2019a laiss\u00e9 \u00e0 personne le soin de prendre le meilleur \u00e0 domicile et de grimper sur la troisi\u00e8me marche du podium."
		},
		{
			"title": "Sport boules \u2013 A domicile, G\u00e9nelard fait le spectacle et remporte sa premi\u00e8re partie - L'infoRmateur de Bourgogne",
			"link": "https://linformateurdebourgogne.com/sport-boules-a-domicile-genelard-fait-le-spectacle-et-remporte-sa-premiere-partie/",
			"pubDate": "Sat, 14 Jun 2025 04:03:40 GMT",
			"image": "https://linformateurdebourgogne.com/wp-content/uploads/2025/06/EX1A4397.jpg",
			"logo": "https://picsum.photos/32/32?grayscale",
			"site_name": "L'infoRmateur de Bourgogne",
			"url": "https://linformateurdebourgogne.com/sport-boules-a-domicile-genelard-fait-le-spectacle-et-remporte-sa-premiere-partie/",
			"description": "Ils sont rest\u00e9s seuls sur le terrain de jeu alors que toutes les autres \u00e9quipes en avaient termin\u00e9 avec la premi\u00e8re partie. Ce fut long mais bon. Longtemps, G\u00e9nelard et M\u00e9tropole Lyon sont rest\u00e9s au coude \u00e0 coude avant que la machine \u00ab\u00a0rose\u00a0\u00bb ne mette le turbo et finisse par\u2026 Suite..."
		},
		{
			"title": "Succ\u00e8s pour la Matinale sport-sant\u00e9 aux thermes - Midi Libre",
			"link": "https://www.midilibre.fr/2025/06/15/succes-pour-la-matinale-sport-sante-aux-thermes-12762826.php",
			"pubDate": "Sun, 15 Jun 2025 03:05:00 GMT",
			"image": "https://images.midilibre.fr/api/v1/images/view/684e38e022867a9573081bb0/large/image.jpg?v=1",
			"logo": "https://picsum.photos/32/32?grayscale",
			"site_name": "midilibre.fr",
			"url": "https://www.midilibre.fr/2025/06/15/succes-pour-la-matinale-sport-sante-aux-thermes-12762826.php",
			"description": "Int\u00e9gr\u00e9e au sein des Thermes de Balaruc depuis le mois de mars 2025, la Maison Sport-Sant\u00e9 a lanc\u00e9 plusieurs initiatives dans une logique de sant\u00e9 globale et de pr\u00e9vention accessible \u00e0 tous les publics. Les matinales..."
		},
		{
			"title": "Troph\u00e9es du sport : votez pour le b\u00e9n\u00e9vole de l'ann\u00e9e - La R\u00e9publique du Centre",
			"link": "https://www.larep.fr/orleans-45000/sports/trophees-du-sport-votez-pour-le-benevole-de-l-annee_14702841/",
			"pubDate": "Sat, 14 Jun 2025 04:30:00 GMT",
			"image": "https://img.centrefrance.com/kVdf2M5VCRoG2ryfBE61K6T4RutBTJ2uhD8o2bl2cUY/rs:fill:1200:800:1:0/g:sm/bG9jYWw6Ly8vMDAvMDAvMDcvNDAvNzYvMjAwMDAwNzQwNzY1Mg.jpg",
			"logo": "https://picsum.photos/32/32?grayscale",
			"site_name": "La R\u00e9publique du Centre",
			"url": "https://www.larep.fr/orleans-45000/sports/trophees-du-sport-votez-pour-le-benevole-de-l-annee_14702841/",
			"description": "La R\u00e9publique du Centre et ses partenaires organisent la premi\u00e8re \u00e9dition des Troph\u00e9es du sport, le 7 octobre. Du 14 juin au 13 septembre, vous pouvez voter pour \u00e9lire le b\u00e9n\u00e9vole de l'ann\u00e9e parmi les trois finalistes."
		},
		{
			"title": "Une belle F\u00eate du sport \u00e0 Bayeux avant le Tour de France, la t\u00eate encore un peu dans les JO de Paris - Ouest-France",
			"link": "https://www.ouest-france.fr/normandie/bayeux-14400/une-belle-fete-du-sport-a-bayeux-avant-le-tour-de-france-la-tete-encore-un-peu-dans-les-jo-de-paris-921e1022-4928-11f0-b660-c6a4d2b5307d",
			"pubDate": "Sun, 15 Jun 2025 13:54:16 GMT",
			"image": "",
			"logo": "https://picsum.photos/32/32?grayscale",
			"site_name": "",
			"url": "",
			"description": ""
		},
		{
			"title": "Jubil\u00e9 du sport, \u00abl\u2019entra\u00eenement quotidien \u00e0 l\u2019amour nous rapproche de la victoire d\u00e9finitive\u00bb - Vatican News",
			"link": "https://www.vaticannews.va/fr/pape/news/2025-06/jubile-sport-homelie-leon-xiv.html",
			"pubDate": "Sun, 15 Jun 2025 10:08:10 GMT",
			"image": "https://www.vaticannews.va/content/dam/vaticannews/agenzie/images/srv/2025/06/15/2025-06-15-giubileo-dello-sport---santa-messa/1749980520753.JPG/_jcr_content/renditions/cq5dam.thumbnail.cropped.1500.844.jpeg",
			"logo": "https://picsum.photos/32/32?grayscale",
			"site_name": "",
			"url": "https://www.vaticannews.va/fr/pape/news/2025-06/jubile-sport-homelie-leon-xiv.html",
			"description": "En la solennit\u00e9 de la Sainte Trinit\u00e9, en cl\u00f4ture du Jubil\u00e9 du monde des sports, L\u00e9on XIV a pr\u00e9sid\u00e9 une messe en la basilique Saint-Pierre. Dans son ..."
		},
		{
			"title": "Saint-\u00c9gr\u00e8ve. La f\u00eate du sport sous le soleil - Le Dauphin\u00e9 Lib\u00e9r\u00e9",
			"link": "https://www.ledauphine.com/societe/2025/06/15/la-fete-du-sport-sous-le-soleil",
			"pubDate": "Sun, 15 Jun 2025 17:57:35 GMT",
			"image": "https://cdn-s-www.ledauphine.com/images/447524C6-B40E-48BE-890E-1D32CAACE07F/FB1200/photo-1750008403.jpg",
			"logo": "https://picsum.photos/32/32?grayscale",
			"site_name": "",
			"url": "https://www.ledauphine.com/societe/2025/06/15/la-fete-du-sport-sous-le-soleil",
			"description": "La f\u00eate du sport s\u2019est tenue dans le parc de la Mairie samedi apr\u00e8s-midi. Trop, c\u2019est trop\u00a0: un soleil ardent a un peu g\u00e2ch\u00e9 la f\u00eate et temp\u00e9r\u00e9 ..."
		},
		{
			"title": "Tournoi de E-sport interarm\u00e9es : la Gendarmerie remporte la premi\u00e8re \u00e9dition du DEF\u2019LAN - Gendarmerie nationale",
			"link": "https://www.gendarmerie.interieur.gouv.fr/gendinfo/actualites/2025/tournoi-de-e-sport-interarmees-la-gendarmerie-remporte-la-premiere-edition-du-def-lan",
			"pubDate": "Sun, 15 Jun 2025 08:11:12 GMT",
			"image": "",
			"logo": "https://picsum.photos/32/32?grayscale",
			"site_name": "",
			"url": "",
			"description": ""
		},
		{
			"title": "\u00ab Sette in Caritellu \u00bb : un club ajaccien pour faire du sport ensemble, sans barri\u00e8re - Corse Net Infos",
			"link": "https://www.corsenetinfos.corsica/Sette-in-Caritellu-un-club-ajaccien-pour-faire-du-sport-ensemble-sans-barriere_a85085.html",
			"pubDate": "Sun, 15 Jun 2025 14:15:00 GMT",
			"image": "https://www.corsenetinfos.corsica/photo/art/grande/89222148-63122627.jpg?v=1749673036",
			"logo": "https://picsum.photos/32/32?grayscale",
			"site_name": "Corse Net Infos - Pure player corse",
			"url": "https://www.corsenetinfos.corsica/Sette-in-Caritellu-un-club-ajaccien-pour-faire-du-sport-ensemble-sans-barriere_a85085.html",
			"description": "Officiellement lanc\u00e9e il y a quelques jours, la structure Sette in Carritellu entend faire bouger les lignes en mati\u00e8re d\u2019acc\u00e8s au sport. Soutenu depuis ses d\u00e9buts par la Ligue Corse de Rugby, ce club \u00e0 vocation inclusive ambitionne de rassembler, d\u00e8s la saison prochaine, des pratiquants valide..."
		},
		{
			"title": "Endurante, ultra-compl\u00e8te et robuste, la montre connect\u00e9e de sport Garmin Instinct 2 co\u00fbte moins de 170 \u20ac sur Amazon - Frandroid",
			"link": "https://www.frandroid.com/bons-plans/2646823_endurante-ultra-complete-et-robuste-la-montre-connectee-de-sport-garmin-instinct-2-coute-moins-de-170-e-sur-amazon",
			"pubDate": "Sun, 15 Jun 2025 15:16:00 GMT",
			"image": "https://c0.lestechnophiles.com/images.frandroid.com/wp-content/uploads/2025/06/garmin-instinct-2.jpg?resize=1600,900&key=4e2cafc3&watermark",
			"logo": "https://picsum.photos/32/32?grayscale",
			"site_name": "Frandroid",
			"url": "https://www.frandroid.com/bons-plans/2646823_endurante-ultra-complete-et-robuste-la-montre-connectee-de-sport-garmin-instinct-2-coute-moins-de-170-e-sur-amazon",
			"description": "R\u00e9sistante et bourr\u00e9e de fonctionnalit\u00e9s, la Garmin Instinct 2 est une montre connect\u00e9e qui peut tout \u00e0 fait accompagner les amateurs de sport. En ce"
		},
		{
			"title": "Valentigney. Sport et solidarit\u00e9 pour 300 jeunes gymnastes r\u00e9unies aux T\u00e2les - L'Est R\u00e9publicain",
			"link": "https://www.estrepublicain.fr/societe/2025/06/15/sport-et-solidarite-pour-300-jeunes-gymnastes-reunies-aux-tales",
			"pubDate": "Sun, 15 Jun 2025 16:07:53 GMT",
			"image": "https://cdn-s-www.estrepublicain.fr/images/5200B6BC-D8A6-48CE-8759-7C16E23F8EE1/FB1200/photo-1750006270.jpg",
			"logo": "https://picsum.photos/32/32?grayscale",
			"site_name": "",
			"url": "https://www.estrepublicain.fr/societe/2025/06/15/sport-et-solidarite-pour-300-jeunes-gymnastes-reunies-aux-tales",
			"description": "L\u2019association La Boroillotte a mobilis\u00e9 ses b\u00e9n\u00e9voles pour accueillir au mieux plusieurs centaines de jeunes gymnastes. Le comit\u00e9 ..."
		},
		{
			"title": "\u00ab Sport Sant\u00e9 2025 \u00bb : d\u00e9veloppez vos activit\u00e9s physiques adapt\u00e9es avec les Maisons Sport Sant\u00e9 de la Ville de Paris - Ville de Paris",
			"link": "https://www.paris.fr/pages/appel-a-projets-sport-sante-2025-developpez-vos-activites-physiques-adaptees-avec-les-maisons-sport-sante-de-la-ville-de-paris-31146",
			"pubDate": "Thu, 12 Jun 2025 07:00:00 GMT",
			"image": "https://cdn.paris.fr/paris/2022/09/29/huge-8f6028b74357fa48d3f71d5229a0f120.jpg",
			"logo": "https://picsum.photos/32/32?grayscale",
			"site_name": "",
			"url": "https://www.paris.fr/pages/appel-a-projets-sport-sante-2025-developpez-vos-activites-physiques-adaptees-avec-les-maisons-sport-sante-de-la-ville-de-paris-31146",
			"description": "Vous proposez de l\u2019activit\u00e9 physique adapt\u00e9e, pr\u00e9sentez votre projet en partenariat avec les Maisons Sport Sant\u00e9 de la Ville de Paris. D\u00e9posez votre dossier sur Paris Asso, jusqu'au 19 juin 2025"
		},
		{
			"title": "INSTITUTIONNEL : S\u00e9ance de cl\u00f4ture du dispositif \"RE'Action Sport Sant\u00e9\", lundi 16 juin \u00e0 Toulon - Presse Agence Sport",
			"link": "http://www.pa-sport.fr/2025/06/15/institutionnel-seance-de-cloture-du-dispositif-reaction-sport-sante-lundi-16-juin-a-toulon/",
			"pubDate": "Sun, 15 Jun 2025 17:25:10 GMT",
			"image": "http://www.pa-sport.fr/wp-content/uploads/image-332.jpeg",
			"logo": "https://picsum.photos/32/32?grayscale",
			"site_name": "Presse Agence Sport",
			"url": "https://www.pa-sport.fr/2025/06/12/institutionnel-seance-de-cloture-du-dispositif-reaction-sport-sante-lundi-16-juin-a-toulon/",
			"description": "Le dispositif \u00ab\u00a0RE\u2019Action Sport Sant\u00e9\u00a0\u00bb c\u00e9l\u00e8bre sa cl\u00f4ture \u00e0 Toulon. Le Comit\u00e9 D\u00e9partemental Olympique et Sportif du Var organise la s\u00e9ance de cl\u00f4ture du dispositif \u00ab\u00a0RE\u2019Action Sport Sant\u00e9\u00a0\u00bb le lundi 16 octobre \u00e0 17h \u00e0 l\u2019\u00e9cole \u00e9l\u00e9mentaire Beaucaire. Ce programme, int\u00e9gr\u00e9 aux \u00ab\u00a0Cit\u00e9s \u00e9ducatives\u00a0\u00bb, vise \u00e0 faciliter l\u2019acc\u00e8s des enfants et des familles \u00e0 la [\u2026]"
		},
		{
			"title": "[Podcasts] Les Grandes Gueules du Sport du 15 juin - 11h/12h - RMC Sport",
			"link": "https://rmcsport.bfmtv.com/replay-emissions/les-grandes-gueules-du-sport/les-grandes-gueules-du-sport-du-15-juin-11h-12h_EN-202506150176.html",
			"pubDate": "Sun, 15 Jun 2025 10:02:47 GMT",
			"image": "https://images.bfmtv.com/RFyvTznpO6UJVMzusvfHtmKpA8g=/0x0:12000x6280/1200x0/images/image_composition_EN-202506150176.jpg",
			"logo": "https://picsum.photos/32/32?grayscale",
			"site_name": "RMC Sport",
			"url": "https://rmcsport.bfmtv.com/replay-emissions/les-grandes-gueules-du-sport/les-grandes-gueules-du-sport-du-15-juin-11h-12h_EN-202506150176.html",
			"description": "La derni\u00e8re ligne droite des Grandes Gueules du Sport... Avec la seconde des GG, la punchline et la nouvelle chronique : les GG \"contre-attaque\" !"
		},
		{
			"title": "Sport professionnel : le S\u00e9nat adopte une proposition de loi visant \u00e0 r\u00e9former particuli\u00e8rement le monde du football - Le Monde.fr",
			"link": "https://www.lemonde.fr/sport/article/2025/06/11/sport-professionnel-le-senat-adopte-une-proposition-de-loi-visant-a-reformer-particulierement-le-monde-du-football_6612111_3242.html",
			"pubDate": "Tue, 10 Jun 2025 22:59:18 GMT",
			"image": "https://img.lemde.fr/2025/06/10/0/27/4945/3297/1440/960/60/0/d75e673_sirius-fs-upload-1-gbd46bourhlt-1749596150013-000-8zz26r.jpg",
			"logo": "https://picsum.photos/32/32?grayscale",
			"site_name": "Le Monde.fr",
			"url": "https://www.lemonde.fr/sport/article/2025/06/11/sport-professionnel-le-senat-adopte-une-proposition-de-loi-visant-a-reformer-particulierement-le-monde-du-football_6612111_3242.html",
			"description": "R\u00e9forme de la gouvernance des ligues professionnelles, r\u00e9mun\u00e9ration des dirigeants plafonn\u00e9e, meilleure redistribution des droits t\u00e9l\u00e9vis\u00e9s\u2026 Le texte a pour ambition de transformer en profondeur l\u2019organisation du sport professionnel. Il doit maintenant \u00eatre examin\u00e9 par les d\u00e9put\u00e9s."
		},
		{
			"title": "Coupe du monde des clubs : le PSG est une \u00ab cible \u00bb - Sport.fr",
			"link": "https://www.sport.fr/football/coupe-du-monde-des-clubs-le-psg-est-une-cible-1354623.shtm",
			"pubDate": "Sun, 15 Jun 2025 18:16:23 GMT",
			"image": "https://www.sport.fr/wp-content/uploads/2025/05/ICONSPORT_260413_0303.jpg",
			"logo": "https://picsum.photos/32/32?grayscale",
			"site_name": "Sport.fr",
			"url": "https://www.sport.fr/football/coupe-du-monde-des-clubs-le-psg-est-une-cible-1354623.shtm",
			"description": "Alors que le Paris Saint-Germain d\u00e9barque en favori pour la Coupe du monde des clubs cet \u00e9t\u00e9, certains anciens joueurs appellent \u00e0 la prudence. Bixente Lizarazu, champion du monde 1998 et ex-joueur du Bayern Munich, a mis en garde le club parisien quant aux attentes \u00e9lev\u00e9es qui p\u00e8sent d\u00e9sormais sur\u2026"
		},
		{
			"title": "Dijon. Faites du sport : rendez-vous le 28 juin au parc de la Colombi\u00e8re - Le Bien Public",
			"link": "https://www.bienpublic.com/culture-loisirs/2025/06/15/faites-du-sport-rendez-vous-le-28-juin-au-parc-de-la-colombiere",
			"pubDate": "Sun, 15 Jun 2025 15:37:07 GMT",
			"image": "https://cdn-s-www.bienpublic.com/images/EDDD5AC5-456F-4A5F-BF7D-C13AFE24F5A5/FB1200/photo-1750008188.jpg",
			"logo": "https://picsum.photos/32/32?grayscale",
			"site_name": "",
			"url": "https://www.bienpublic.com/culture-loisirs/2025/06/15/faites-du-sport-rendez-vous-le-28-juin-au-parc-de-la-colombiere",
			"description": "Une quarantaine d\u2019associations sportives et de sant\u00e9 seront pr\u00e9sentes au parc de la Colombi\u00e8re \u00e0 Dijon, samedi 28\u00a0juin. Permettant au public de ..."
		},
		{
			"title": "Le jiu-jitsu br\u00e9silien, ce sport de combat qui muscle sans brutalit\u00e9 - TF1 Info",
			"link": "https://www.tf1info.fr/sante/le-jiu-jitsu-bresilien-ce-sport-de-combat-qui-muscle-sans-brutalite-2374900.html",
			"pubDate": "Sun, 15 Jun 2025 08:00:00 GMT",
			"image": "https://photos.tf1info.fr/images/1280/720/jiu-jitsu-bresilien-0c6dd3-0@1x.jpeg?overlayImage=bG9nby10ZjFpbmZvLWRlZmF1bHQucG5n&overlayWidth=18&overlayGravity=northwest&s=78c802",
			"logo": "https://picsum.photos/32/32?grayscale",
			"site_name": "TF1 INFO",
			"url": "https://www.tf1info.fr/sante/le-jiu-jitsu-bresilien-ce-sport-de-combat-qui-muscle-sans-brutalite-2374900.html",
			"description": "[VID\u00c9O] Le jiu-jitsu br\u00e9silien allie technique, souplesse et strat\u00e9gie. Ce sport de combat fait travailler le corps en profondeur. Au fil des entra\u00eenements, il sculpte le corps, d\u00e9veloppe la confiance en soi et am\u00e9liore la gestion du stress. - Le jiu-jitsu br\u00e9silien, ce sport de combat qui muscle sans brutalit\u00e9 (Sant\u00e9 et bien \u00eatre)."
		},
		{
			"title": "L\u2019OM offre un million d\u2019euro pour cet espoir danois - Sport.fr",
			"link": "https://www.sport.fr/football/lom-offre-un-million-deuro-pour-cet-espoir-danois-1354735.shtm",
			"pubDate": "Sun, 15 Jun 2025 17:47:42 GMT",
			"image": "https://www.sport.fr/wp-content/uploads/2025/06/ICONSPORT_194795_0320.jpg",
			"logo": "https://picsum.photos/32/32?grayscale",
			"site_name": "Sport.fr",
			"url": "https://www.sport.fr/football/lom-offre-un-million-deuro-pour-cet-espoir-danois-1354735.shtm",
			"description": "L\u2019Olympique de Marseille a lanc\u00e9 les premiers jalons pour s\u2019attacher les services de Roony Bardghji, jeune ailier de 19 ans \u00e9voluant \u00e0 Copenhague. Selon Foot Mercato, le club phoc\u00e9en a d\u00e9pos\u00e9 une premi\u00e8re offre d\u2019environ un million d\u2019euros. Ce montant reste modeste, compte tenu de la fin prochaine du contrat\u2026"
		},
		{
			"title": "Voreppe. Le samedi \u00e9tait plac\u00e9 sous le signe du sport avec les Voreppiades - Le Dauphin\u00e9 Lib\u00e9r\u00e9",
			"link": "https://www.ledauphine.com/culture-loisirs/2025/06/15/le-samedi-etait-place-sous-le-signe-du-sport-avec-les-voreppiades",
			"pubDate": "Sun, 15 Jun 2025 17:17:36 GMT",
			"image": "https://cdn-s-www.ledauphine.com/images/DE062AAA-8946-49C4-A734-50B0D4CFB081/FB1200/photo-1750007570.jpg",
			"logo": "https://picsum.photos/32/32?grayscale",
			"site_name": "",
			"url": "https://www.ledauphine.com/culture-loisirs/2025/06/15/le-samedi-etait-place-sous-le-signe-du-sport-avec-les-voreppiades",
			"description": "L\u2019\u00e9dition 2025 des Voreppiades a permis \u00e0 de nombreux enfants enthousiastes de s\u2019essayer \u00e0 une multitude de disciplines, alors que les ..."
		},
		{
			"title": "Sport. Jamais rassasi\u00e9, le paratriathl\u00e8te yvetotais Alexis Hanquinquant sacr\u00e9 pour la huiti\u00e8me fois champion d'Europe - lecourriercauchois.fr",
			"link": "https://www.lecourriercauchois.fr/actualite-384788-sport-jamais-rassasie-le-paratriathlete-yvetotais-alexis-hanquinquant-sacre-pour-la-huitieme-fois-champion-d-europe",
			"pubDate": "Sun, 15 Jun 2025 16:10:00 GMT",
			"image": "https://medias.lecourriercauchois.fr/photos/1200/384788/?v=1750006498",
			"logo": "https://picsum.photos/32/32?grayscale",
			"site_name": "lecourriercauchois.fr",
			"url": "https://www.lecourriercauchois.fr/actualite-384788-sport-jamais-rassasie-le-paratriathlete-yvetotais-alexis-hanquinquant-sacre-pour-la-huitieme-fois-champion-d-europe",
			"description": "Totalement ma\u00eetre de son sujet samedi \u00e0 Besan\u00e7on, le paratriathl\u00e8te yvetotais\u00a0a obtenu son huiti\u00e8me titre europ\u00e9en en PTS4."
		},
		{
			"title": "Chamb\u00e9ry - La Savoie met \u00e0 l\u2019honneur la rel\u00e8ve du tennis - Savoie News",
			"link": "https://www.savoie-news.fr/reportages/sport-de-raquette/article/la-savoie-met-a-l-rsquo-honneur-la-releve-du-tennis",
			"pubDate": "Sun, 15 Jun 2025 15:05:00 GMT",
			"image": "https://www.savoie-news.fr/uploads/11683-684edbf94b9d3-minia-ytb-84-jpg.jpg",
			"logo": "https://picsum.photos/32/32?grayscale",
			"site_name": "Savoie News",
			"url": "https://www.savoie-news.fr/reportages/sport-de-raquette/article/la-savoie-met-a-l-rsquo-honneur-la-releve-du-tennis",
			"description": " Le 14 juin, le club de tennis de Chamb\u00e9ry Bissy a accueilli la remise des prix des championnats jeunes 2025, r\u00e9compensant les performances indivi..."
		},
		{
			"title": "L\u2019OM d\u00e9voile son nouveau maillot 2025-2026 (photo) - Sport.fr",
			"link": "https://www.sport.fr/football/lom-devoile-son-nouveau-maillot-2025-2026-photo-1354630.shtm",
			"pubDate": "Sun, 15 Jun 2025 16:44:00 GMT",
			"image": "https://www.sport.fr/wp-content/uploads/2025/05/ICONSPORT_259814_0019-1.jpg",
			"logo": "https://picsum.photos/32/32?grayscale",
			"site_name": "Sport.fr",
			"url": "https://www.sport.fr/football/lom-devoile-son-nouveau-maillot-2025-2026-photo-1354630.shtm",
			"description": "C\u2019est d\u00e9sormais officiel : l\u2019Olympique de Marseille a pr\u00e9sent\u00e9 son nouveau maillot domicile pour la saison 2025-2026. Aper\u00e7u pour la premi\u00e8re fois lors du concert de Jul au V\u00e9lodrome le 24 mai, le maillot conserve les couleurs embl\u00e9matiques du club \u2014 blanc et bleu ciel \u2014 mais se distingue par\u2026"
		},
		{
			"title": "Saint-Alban : l\u2019association Penthi\u00e8vre Sport Sant\u00e9 compte 239 adh\u00e9rents - Le T\u00e9l\u00e9gramme",
			"link": "https://www.letelegramme.fr/cotes-d-armor/saint-alban-22400/saint-alban-lassociation-penthievre-sport-sante-compte-239-adherents-6836318.php",
			"pubDate": "Sun, 15 Jun 2025 13:36:38 GMT",
			"image": "https://media.letelegramme.fr/api/v1/images/view/684ecc66d863ebb1470ab2d3/web_golden_xxl/684ecc66d863ebb1470ab2d3.1",
			"logo": "https://picsum.photos/32/32?grayscale",
			"site_name": "Le T\u00e9l\u00e9gramme",
			"url": "https://www.letelegramme.fr/cotes-d-armor/saint-alban-22400/saint-alban-lassociation-penthievre-sport-sante-compte-239-adherents-6836318.php",
			"description": "Cr\u00e9\u00e9e en 2017, l\u2019association Penthi\u00e8vre Sport Sant\u00e9, initialement Bien-\u00eatre, sport sant\u00e9, compte aujourd\u2019hui 239 adh\u00e9rents sur les communes du Penthi\u00e8vre"
		},
		{
			"title": "Mondiaux de judo: les images spectaculaires de Martha Fawaz, inanim\u00e9e apr\u00e8s un \u00e9tranglement - RMC Sport",
			"link": "https://rmcsport.bfmtv.com/judo/mondiaux-de-judo-les-images-spectaculaires-de-martha-fawaz-inanimee-apres-un-etranglement_AP-202506150223.html",
			"pubDate": "Sun, 15 Jun 2025 12:02:27 GMT",
			"image": "https://images.bfmtv.com/y9hqFd_9bhoBaMWimGkuYWjNnPU=/0x1:1136x640/images/Martha-Fawaz-battue-aux-Mondiaux-de-judo-2097404.jpg",
			"logo": "https://picsum.photos/32/32?grayscale",
			"site_name": "RMC Sport",
			"url": "https://rmcsport.bfmtv.com/judo/mondiaux-de-judo-les-images-spectaculaires-de-martha-fawaz-inanimee-apres-un-etranglement_AP-202506150223.html",
			"description": "La judokate fran\u00e7aise Martha Fawaz s'est inclin\u00e9e face \u00e0 l'Ouzb\u00e8ke Shukurjon Aminova en 16e de finale des -57kg dimanche \u00e0 l'occasion de la 3e journ\u00e9e des Mondiaux de judo \u00e0 Budapest. Un revers par ippon apr\u00e8s un \u00e9tranglement qui a mis la Tricolore tellement KO qu'elle a d\u00fb \u00eatre \u00e9vacu\u00e9e du tatami..."
		},
		{
			"title": "Ard\u00e8che : un bonus s\u00e9niors pour adh\u00e9rer \u00e0 un club de sport - francebleu.fr",
			"link": "https://www.francebleu.fr/infos/sante-sciences/ardeche-un-bonus-seniors-pour-adherer-a-un-club-de-sport-2659101",
			"pubDate": "Sun, 15 Jun 2025 04:31:31 GMT",
			"image": "https://www.francebleu.fr/s3/cruiser-production-eu3/2025/06/bc93c589-0485-4f83-9ec9-dda657969c08/1200x680_sc_874485-w2b4kr6jdd-whr.jpg",
			"logo": "https://picsum.photos/32/32?grayscale",
			"site_name": "ici, le m\u00e9dia de la vie locale",
			"url": "https://www.francebleu.fr/infos/sante-sciences/ardeche-un-bonus-seniors-pour-adherer-a-un-club-de-sport-2659101",
			"description": "Le conseil d\u00e9partemental de l'Ard\u00e8che a vot\u00e9 un bonus s\u00e9niors de 30 \u20ac pour chaque ard\u00e9chois de plus de 70 ans qui souhaiterait adh\u00e9rer \u00e0 un club de sport. "
		},
		{
			"title": "Le tir \u00e0 l\u2019arc \u00e0 l\u2019honneur dans \u00ab 100 % sport en Picardie \u00bb ce lundi 16 juin - Courrier picard",
			"link": "https://www.courrier-picard.fr/id638628/article/2025-06-15/le-tir-larc-lhonneur-dans-100-sport-en-picardie-ce-lundi-16-juin",
			"pubDate": "Sun, 15 Jun 2025 14:57:56 GMT",
			"image": "",
			"logo": "https://picsum.photos/32/32?grayscale",
			"site_name": "",
			"url": "",
			"description": ""
		},
		{
			"title": "Les Estivales \u00c9questres 2025 : sport, f\u00eate et passion au galop ! - roubaixxl",
			"link": "https://www.roubaixxl.fr/estivales-equestres-roubaix-2025/",
			"pubDate": "Sun, 15 Jun 2025 06:35:28 GMT",
			"image": "https://www.roubaixxl.fr/wp-content/uploads/2025/06/les-estivales-equestres.jpg",
			"logo": "https://picsum.photos/32/32?grayscale",
			"site_name": "ROUBAIXXL",
			"url": "https://www.roubaixxl.fr/estivales-equestres-roubaix-2025/",
			"description": "Les 21 et 22 juin, vivez un week-end festif au Club Hippique de Roubaix : comp\u00e9titions, animations, village partenaires et soir\u00e9e DJ en plein air !"
		},
		{
			"title": "Signalement -Une nouvelle obligation d'affichage dans les salles de sport - Service-Public.fr",
			"link": "https://entreprendre.service-public.fr/actualites/A18276",
			"pubDate": "Mon, 09 Jun 2025 22:00:00 GMT",
			"image": "https://www.service-public.fr/webapp/images/actu/extralarge/I7615_Salle de sport.jpg",
			"logo": "https://picsum.photos/32/32?grayscale",
			"site_name": "",
			"url": "https://entreprendre.service-public.fr/actualites/A18276",
			"description": "Les salles de sport ont l'obligation d'informer des dispositifs de pr\u00e9vention, de signalement et d'accompagnement des victimes de violences ou de discrimination"
		},
		{
			"title": "La f\u00eate de la musique mais aussi du th\u00e9\u00e2tre, du sport pour les seniors, la m\u00e9moire de l\u2019appel du 18-Juin, la s\u00e9curit\u00e9 \u00e0 Kermoysan\u2026 Ce qui vous attend cette semaine \u00e0 Quimper - Le T\u00e9l\u00e9gramme",
			"link": "https://www.letelegramme.fr/finistere/quimper-29000/la-fete-de-la-musique-mais-aussi-du-theatre-du-sport-pour-les-seniors-la-memoire-de-lappel-du-18-juin-la-securite-a-kermoysan-ce-qui-vous-attend-cette-semaine-a-quimper-6836328.php",
			"pubDate": "Sun, 15 Jun 2025 16:00:03 GMT",
			"image": "https://media.letelegramme.fr/api/v1/images/view/684ecdf7ca10f617700a9313/web_golden_xxl/684ecdf7ca10f617700a9313.1",
			"logo": "https://picsum.photos/32/32?grayscale",
			"site_name": "Le T\u00e9l\u00e9gramme",
			"url": "https://www.letelegramme.fr/finistere/quimper-29000/la-fete-de-la-musique-mais-aussi-du-theatre-du-sport-pour-les-seniors-la-memoire-de-lappel-du-18-juin-la-securite-a-kermoysan-ce-qui-vous-attend-cette-semaine-a-quimper-6836328.php",
			"description": "Th\u00e9\u00e2tre, sport pour les seniors, f\u00eate de la musique, bien vivre \u00e0 Kermoysan, appel du 18-Juin\u2026 voici une liste non exhaustive de ce qui vous attend cette semaine \u00e0 Quimper."
		},
		{
			"title": "VID\u00c9O \u2013 Une nouvelle roue perdue chez IDEC Sport - autohebdo.fr",
			"link": "https://www.autohebdo.fr/breves/endurance/video-une-nouvelle-roue-perdue-chez-idec-sport.html",
			"pubDate": "Sun, 15 Jun 2025 11:08:00 GMT",
			"image": "https://www.autohebdo.fr/app/uploads/2025/06/DPPI_02625007_270.jpg",
			"logo": "https://picsum.photos/32/32?grayscale",
			"site_name": "AutoHebdo",
			"url": "https://www.autohebdo.fr/breves/endurance/video-une-nouvelle-roue-perdue-chez-idec-sport.html",
			"description": "IDEC Sport a vu ses espoirs de podium partir en fum\u00e9e apr\u00e8s avoir perdu la roue arri\u00e8re droite de son Oreca n\u00b028."
		},
		{
			"title": "\"Pass\u00e9 la quarantaine, on se pose les bonnes questions\" : ce Cadurcien se lance dans une reconversion pour devenir \u00e9ducateur sportif - ladepeche.fr",
			"link": "https://www.ladepeche.fr/2025/06/15/passe-la-quarantaine-on-se-pose-les-bonnes-questions-ce-cadurcien-se-lance-dans-une-reconversion-pour-devenir-educateur-sportif-12763324.php",
			"pubDate": "Sun, 15 Jun 2025 14:16:00 GMT",
			"image": "https://images.ladepeche.fr/api/v1/images/view/684e95ebbd178a26850bcf5e/large/image.jpg?v=1",
			"logo": "https://picsum.photos/32/32?grayscale",
			"site_name": "ladepeche.fr",
			"url": "https://www.ladepeche.fr/2025/06/15/passe-la-quarantaine-on-se-pose-les-bonnes-questions-ce-cadurcien-se-lance-dans-une-reconversion-pour-devenir-educateur-sportif-12763324.php",
			"description": "\u00c0 43 ans, Nicolas Cescon, salari\u00e9 dans le transport \u00e0 Cahors, a d\u00e9cid\u00e9 de changer de cap. Passionn\u00e9 de musculation, il se forme pour devenir \u00e9ducateur sportif et s\u2019investit dans la promotion de l\u2019halt\u00e9rophilie."
		},
		{
			"title": "Loire-Atlantique / Vend\u00e9e : comment le sport a sauv\u00e9 la vie de S\u00e9bastien, 53 ans, atteint d\u2019un cancer - Actu.fr",
			"link": "https://actu.fr/pays-de-la-loire/saint-andre-des-eaux_44151/loire-atlantique-vendee-comment-le-sport-a-sauve-la-vie-de-sebastien-53-ans-atteint-dun-cancer_62771812.html",
			"pubDate": "Sun, 15 Jun 2025 15:00:02 GMT",
			"image": "https://static.actu.fr/uploads/2025/06/3fc035544c48653d035544c4847d03v.jpg",
			"logo": "https://picsum.photos/32/32?grayscale",
			"site_name": "actu.fr",
			"url": "https://actu.fr/pays-de-la-loire/saint-andre-des-eaux_44151/loire-atlantique-vendee-comment-le-sport-a-sauve-la-vie-de-sebastien-53-ans-atteint-dun-cancer_62771812.html",
			"description": "Le 22\u00a0juin 2025, S\u00e9bastien Philippe prendra le d\u00e9part de l\u2019Ironman des Sables-d\u2019Olonne. Un d\u00e9fi exceptionnel pour cet habitant de Saint-Andr\u00e9-des-Eaux atteint d\u2019un cancer rare."
		},
		{
			"title": "Le futsal f\u00e9minin obtient son Championnat de France ! - Sport.fr",
			"link": "https://www.sport.fr/omnisports/le-futsal-feminin-obtient-son-championnat-de-france-1354764.shtm",
			"pubDate": "Sun, 15 Jun 2025 20:07:00 GMT",
			"image": "https://www.sport.fr/wp-content/uploads/2025/06/ICONSPORT_251379_0017.jpg",
			"logo": "https://picsum.photos/32/32?grayscale",
			"site_name": "Sport.fr",
			"url": "https://www.sport.fr/omnisports/le-futsal-feminin-obtient-son-championnat-de-france-1354764.shtm",
			"description": "C\u2019est d\u00e9sormais officiel : le futsal f\u00e9minin fran\u00e7ais aura son propre Championnat national \u00e0 partir de la saison 2026-2027. Lors de son assembl\u00e9e g\u00e9n\u00e9rale organis\u00e9e samedi, la F\u00e9d\u00e9ration fran\u00e7aise de football (FFF) a vot\u00e9 massivement en faveur de ce projet. Selon les informations de L'\u00c9quipe, la cr\u00e9ation de cette nouvelle\u2026"
		},
		{
			"title": "Sports. La r\u00e9daction d\u2019Ouest-France cherche des correspondants en Mayenne . Sport - Maville",
			"link": "https://guingamp.maville.com/sport/infos/detail_-sports.-la-redaction-d-ouest-france-cherche-des-correspondants-en-mayenne-_-6854812_actu.Htm",
			"pubDate": "Sun, 15 Jun 2025 16:55:00 GMT",
			"image": "https://maville.com/photosmvi/2025/06/15/P35292555D6854812G_crop_1080-600_.jpg",
			"logo": "https://picsum.photos/32/32?grayscale",
			"site_name": "",
			"url": "",
			"description": "Sport Guingamp Sports La r\u00e9daction dOuest-France cherche des correspondants en Mayenne - La... Guingamp"
		},
		{
			"title": "Rugby (Championnat de France de R\u00e9gionale 1, quart de finale) : Saint-C\u00e9r\u00e9 : le r\u00eave continue - ladepeche.fr",
			"link": "https://www.ladepeche.fr/2025/06/15/rugby-championnat-de-france-de-regionale-1-quart-de-finale-saint-cere-le-reve-continue-12763894.php",
			"pubDate": "Sun, 15 Jun 2025 18:31:00 GMT",
			"image": "https://images.ladepeche.fr/api/v1/images/view/684f073e8c91a3cb7d07226e/large/image.jpg?v=1",
			"logo": "https://picsum.photos/32/32?grayscale",
			"site_name": "ladepeche.fr",
			"url": "https://www.ladepeche.fr/2025/06/15/rugby-championnat-de-france-de-regionale-1-quart-de-finale-saint-cere-le-reve-continue-12763894.php",
			"description": "Saint-C\u00e9r\u00e9 25 \u2013 Moissac 22 Au Stade de la Douve \u00e0 Luzech. Arbitres\u00a0: MM.\u00a0J\u00e9r\u00e9my Veyssi\u00e8re, Michel Cazelles et Alexis Gilot. Mi-temps\u00a0: 15-10. Pour Saint-C\u00e9r\u00e9 Rugby\u00a0: 1E Dailly Larribe (57e)\u00a0; 1T et 6P Bonnet (10e,..."
		},
		{
			"title": "Rugby (quart de finale du championnat de France de F\u00e9d\u00e9rale 3). Caussade tombe la t\u00eate tr\u00e8s haute - ladepeche.fr",
			"link": "https://www.ladepeche.fr/2025/06/15/rugby-quart-de-finale-du-championnat-de-france-de-federale-3-caussade-tombe-la-tete-tres-haute-12763905.php",
			"pubDate": "Sun, 15 Jun 2025 17:57:00 GMT",
			"image": "https://images.ladepeche.fr/api/v1/images/view/684f085fa436090eb90733e0/large/image.jpg?v=1",
			"logo": "https://picsum.photos/32/32?grayscale",
			"site_name": "ladepeche.fr",
			"url": "https://www.ladepeche.fr/2025/06/15/rugby-quart-de-finale-du-championnat-de-france-de-federale-3-caussade-tombe-la-tete-tres-haute-12763905.php",
			"description": "Face \u00e0 des Aveyronnais qui devaient les manger tout cru, les Tarn-et-Garonnais ont fait mieux que de se d\u00e9fendre mais doivent finalement baisser pavillon."
		},
		{
			"title": "Longvic. D\u00e9fi des CP : \u00ab Le but, c\u2019est de promouvoir le sport \u00bb - Le Bien Public",
			"link": "https://www.bienpublic.com/sport/2025/06/15/defi-des-cp-le-but-c-est-de-promouvoir-le-sport",
			"pubDate": "Sun, 15 Jun 2025 15:13:17 GMT",
			"image": "https://cdn-s-www.bienpublic.com/images/3E7AEA6E-4784-41A0-A67E-5DFAEAE7A7C7/FB1200/photo-1750008087.jpg",
			"logo": "https://picsum.photos/32/32?grayscale",
			"site_name": "",
			"url": "https://www.bienpublic.com/sport/2025/06/15/defi-des-cp-le-but-c-est-de-promouvoir-le-sport",
			"description": "Jeudi 12\u00a0juin, environ 70 \u00e9l\u00e8ves de CP se sont rencontr\u00e9s pour un d\u00e9fi sportif sur les terrains de football de l\u2019espace Jean-Bouhey \u00e0 Longvic. ..."
		},
		{
			"title": "Cette p\u00e9pite de l\u2019OL met la Croatie \u00e0 ses pieds ! - Sport.fr",
			"link": "https://www.sport.fr/football/cette-pepite-de-lol-met-la-croatie-a-ses-pieds-1354792.shtm",
			"pubDate": "Sun, 15 Jun 2025 20:08:38 GMT",
			"image": "https://www.sport.fr/wp-content/uploads/2024/02/Icon_ICONSPORT__DSC1685.jpg",
			"logo": "https://picsum.photos/32/32?grayscale",
			"site_name": "Sport.fr",
			"url": "https://www.sport.fr/football/cette-pepite-de-lol-met-la-croatie-a-ses-pieds-1354792.shtm",
			"description": "Jeune d\u00e9fenseur droit de 20 ans, T\u00e9o Barisic fait d\u00e9j\u00e0 parler de lui bien au-del\u00e0 des fronti\u00e8res fran\u00e7aises.\u00a0 Apr\u00e8s ses d\u00e9buts professionnels avec l\u2019Olympique Lyonnais face \u00e0 Angers en fin de saison, le capitaine de la r\u00e9serve lyonnaise suscite l\u2019int\u00e9r\u00eat de plusieurs clubs, notamment en Croatie. Selon Sportske et Germanijak,\u2026"
		},
		{
			"title": "Basket-ball (finale d\u2019Occitanie de R\u00e9gionale 2 masculine). Caussade fait craquer Auch en quatre minutes - ladepeche.fr",
			"link": "https://www.ladepeche.fr/2025/06/15/basket-ball-finale-doccitanie-de-regionale-2-masculine-caussade-fait-craquer-auch-en-quatre-minutes-12764010.php",
			"pubDate": "Sun, 15 Jun 2025 19:10:00 GMT",
			"image": "https://images.ladepeche.fr/api/v1/images/view/684f1956320e964a2a0255ba/large/image.jpg?v=1",
			"logo": "https://picsum.photos/32/32?grayscale",
			"site_name": "ladepeche.fr",
			"url": "https://www.ladepeche.fr/2025/06/15/basket-ball-finale-doccitanie-de-regionale-2-masculine-caussade-fait-craquer-auch-en-quatre-minutes-12764010.php",
			"description": "Les Tarn-et-Garonnais concluent leur saison exceptionnelle sur un titre face aux voisins auscitains."
		},
		{
			"title": "Padel AC Paris Nord / Roissy : un nouveau temple du sport \u00e0 deux pas de la capitale - Padel Magazine",
			"link": "https://padelmagazine.fr/padel-ac-paris-nord-roissy-un-nouveau-temple-du-sport-a-deux-pas-de-la-capitale/",
			"pubDate": "Sun, 15 Jun 2025 06:55:00 GMT",
			"image": "https://padelmagazine.fr/wp-content/uploads/2025/06/Padel-AC-Roissy.jpg",
			"logo": "https://picsum.photos/32/32?grayscale",
			"site_name": "Padel Magazine",
			"url": "https://padelmagazine.fr/padel-ac-paris-nord-roissy-un-nouveau-temple-du-sport-a-deux-pas-de-la-capitale/",
			"description": "\u00c0 seulement 14 kilom\u00e8tres de Paris, un nouveau complexe multisports s\u2019appr\u00eate \u00e0 dynamiser la sc\u00e8ne sportive francilienne \u00e0 partir de la rentr\u00e9e de septembre 2025. Le Padel AC Paris Nord / Roissy, situ\u00e9 au c\u0153ur de Paris Nord 2, entend devenir une r\u00e9f\u00e9rence en mati\u00e8re de padel, d\u2019escalade de bloc et de fitness premium. Install\u00e9"
		},
		{
			"title": "Basket-ball (finale d\u2019Occitanie de R\u00e9gionale 2 f\u00e9minine). Caussade/Gimbelet au bout du suspense - ladepeche.fr",
			"link": "https://www.ladepeche.fr/2025/06/15/basket-ball-finale-doccitanie-de-regionale-2-feminine-caussadegimbelet-au-bout-du-suspense-12764019.php",
			"pubDate": "Sun, 15 Jun 2025 19:20:00 GMT",
			"image": "https://images.ladepeche.fr/api/v1/images/view/684f1ba987091250a20fce03/large/image.jpg?v=1",
			"logo": "https://picsum.photos/32/32?grayscale",
			"site_name": "ladepeche.fr",
			"url": "https://www.ladepeche.fr/2025/06/15/basket-ball-finale-doccitanie-de-regionale-2-feminine-caussadegimbelet-au-bout-du-suspense-12764019.php",
			"description": "Apr\u00e8s avoir vu les gar\u00e7ons s\u2019imposer de deux petits points, les Tarn-et-Garonnaises s\u2019imposent elles aussi d\u2019une courte t\u00eate, pour un formidable doubl\u00e9."
		},
		{
			"title": "PSG : Achraf Hakimi assume le r\u00f4le de favori - Sport.fr",
			"link": "https://www.sport.fr/football/psg-achraf-hakimi-assume-le-role-de-favori-1354619.shtm",
			"pubDate": "Sun, 15 Jun 2025 17:17:24 GMT",
			"image": "https://www.sport.fr/wp-content/uploads/2025/05/ICONSPORT_259587_0665.jpg",
			"logo": "https://picsum.photos/32/32?grayscale",
			"site_name": "Sport.fr",
			"url": "https://www.sport.fr/football/psg-achraf-hakimi-assume-le-role-de-favori-1354619.shtm",
			"description": "\u00c0 l\u2019approche de la Coupe du monde des clubs, le Paris Saint-Germain aborde la comp\u00e9tition avec l\u2019\u00e9tiquette de grand favori. Un statut que le club francilien doit \u00e0 son sacre historique en Ligue des Champions cette saison. Pr\u00e9sent en conf\u00e9rence de presse, Achraf Hakimi, l\u2019un des hommes forts du PSG,\u2026"
		},
		{
			"title": "Athl\u00e9tisme : le perchiste Armand Duplantis porte son record du monde \u00e0 6,28 m - europe1.fr",
			"link": "https://www.europe1.fr/sport/athletisme-le-perchiste-armand-duplantis-porte-son-record-du-monde-a-628-m-758860",
			"pubDate": "Sun, 15 Jun 2025 20:01:03 GMT",
			"image": "https://www.europe1.fr/lmnr/var/europe1/storage/media/image/2025/06/15/21/043_sw_v7mojpzck2k-2-1.jpg?VersionId=6hCbP4gt0QcZ0ij8tcKgqsp4JtZ2VdHx",
			"logo": "https://picsum.photos/32/32?grayscale",
			"site_name": "",
			"url": "https://www.europe1.fr/sport/athletisme-le-perchiste-armand-duplantis-porte-son-record-du-monde-a-628-m-758860",
			"description": "Devant son public, Armand Duplantis a am\u00e9lior\u00e9, pour la 12e fois de sa carri\u00e8re, son record du monde du saut \u00e0 la perche. Cette fois, le Su\u00e9dois a franchit la barre des 6,28 m\u00e8tres d\u00e8s son premier essai. Son pr\u00e9c\u00e9dent record datait d'il y a \u00e0 peine quatre mois, \u00e0 6,27 m\u00e8tres. "
		},
		{
			"title": "Sarah-L\u00e9onie Cysique en bronze aux Mondiaux - Sport.fr",
			"link": "https://www.sport.fr/judo/sarah-leonie-cysique-en-bronze-aux-mondiaux-1354711.shtm",
			"pubDate": "Sun, 15 Jun 2025 17:08:00 GMT",
			"image": "https://www.sport.fr/wp-content/uploads/2023/05/Icon_6947.jpg",
			"logo": "https://picsum.photos/32/32?grayscale",
			"site_name": "Sport.fr",
			"url": "https://www.sport.fr/judo/sarah-leonie-cysique-en-bronze-aux-mondiaux-1354711.shtm",
			"description": "Sarah-L\u00e9onie Cysique a enfin obtenu sa premi\u00e8re m\u00e9daille mondiale individuelle ce dimanche chez les -57 kg. Oppos\u00e9e \u00e0 l\u2019Ouzb\u00e8ke Shukurjon Aminova pour la troisi\u00e8me place, la Fran\u00e7aise a fait preuve de d\u00e9termination en s\u2019imposant au golden score. D\u00e9\u00e7ue apr\u00e8s sa d\u00e9faite en demi-finale contre la Japonaise Momo Tamaoki, la double\u2026"
		},
		{
			"title": "Rugby (Championnat de France de F\u00e9d\u00e9rale 2, quart de finale) : Cahors Rugby s'invite dans le dernier carr\u00e9 - ladepeche.fr",
			"link": "https://www.ladepeche.fr/2025/06/15/rugby-championnat-de-france-de-federale-2-quart-de-finale-cahors-rugby-sinvite-dans-le-dernier-carre-12763850.php",
			"pubDate": "Sun, 15 Jun 2025 17:25:00 GMT",
			"image": "https://images.ladepeche.fr/api/v1/images/view/684efe979ddd1a9008045462/large/image.jpg?v=1",
			"logo": "https://picsum.photos/32/32?grayscale",
			"site_name": "ladepeche.fr",
			"url": "https://www.ladepeche.fr/2025/06/15/rugby-championnat-de-france-de-federale-2-quart-de-finale-cahors-rugby-sinvite-dans-le-dernier-carre-12763850.php",
			"description": "Cahors 26 - Saint Malo 19 Au Stade municipal Complexe des Champs de L\u2019Ile \u00e0 Saint-Maixent-L\u2019Ecole. Mi-temps : 13-10 ; Arbitres : MM. Romain Fi\u00e8vre, David Reboursi\u00e8re et William Bouleau (Pays de Loire). Pour Cahors..."
		},
		{
			"title": "Euro Espoirs : l\u2019Angleterre freine, l\u2019Ukraine se relance - Sport.fr",
			"link": "https://www.sport.fr/football/euro-espoirs-langleterre-freine-lukraine-se-relance-1354767.shtm",
			"pubDate": "Sun, 15 Jun 2025 18:06:32 GMT",
			"image": "https://www.sport.fr/wp-content/uploads/2024/11/ICONSPORT_239650_0026.webp",
			"logo": "https://picsum.photos/32/32?grayscale",
			"site_name": "Sport.fr",
			"url": "https://www.sport.fr/football/euro-espoirs-langleterre-freine-lukraine-se-relance-1354767.shtm",
			"description": "Dans le groupe B, l\u2019Angleterre a conc\u00e9d\u00e9 un nul frustrant face \u00e0 la Slov\u00e9nie (0-0), malgr\u00e9 sa domination et la titularisation de Rowe, joueur de Marseille. Apr\u00e8s une victoire convaincante contre la R\u00e9publique tch\u00e8que, les Anglais restent leaders provisoires. De son c\u00f4t\u00e9, dans le groupe D, l\u2019Ukraine a rebondi apr\u00e8s\u2026"
		},
		{
			"title": "Karel Geraerts pr\u00eat \u00e0 relancer Reims - Sport.fr",
			"link": "https://www.sport.fr/football/karel-geraerts-pret-a-relancer-reims-1354696.shtm",
			"pubDate": "Sun, 15 Jun 2025 17:57:00 GMT",
			"image": "https://www.sport.fr/wp-content/uploads/2024/12/ICONSPORT_246316_0001.webp",
			"logo": "https://picsum.photos/32/32?grayscale",
			"site_name": "Sport.fr",
			"url": "https://www.sport.fr/football/karel-geraerts-pret-a-relancer-reims-1354696.shtm",
			"description": "Le Stade de Reims tient enfin son nouvel entra\u00eeneur. Selon L\u2019\u00c9quipe, le technicien belge Karel Geraerts est sur le point de s\u2019engager pour deux saisons avec le club champenois, fra\u00eechement rel\u00e9gu\u00e9 en Ligue 2. \u00c0 43 ans, l\u2019ex-coach de l\u2019Union Saint-Gilloise succ\u00e9dera \u00e0 Samba Diawara, qui pourrait conserver un r\u00f4le\u2026"
		},
		{
			"title": "Sport. La chronique de Valentin Deudon : Paris 2024 en po\u00e9sie - Sud Ouest",
			"link": "https://www.sudouest.fr/sport/jeux-olympiques/sport-la-chronique-de-valentin-deudon-paris-2024-en-poesie-24850758.php",
			"pubDate": "Sun, 15 Jun 2025 06:18:00 GMT",
			"image": "https://media.sudouest.fr/24850758/1200x-1/valentin-deudon.jpg",
			"logo": "https://picsum.photos/32/32?grayscale",
			"site_name": "SudOuest.fr",
			"url": "https://www.sudouest.fr/sport/jeux-olympiques/sport-la-chronique-de-valentin-deudon-paris-2024-en-poesie-24850758.php",
			"description": ""
		},
		{
			"title": "Sports de combat \u00e0 Saintes : le champion du monde Figuereido Landman a assum\u00e9 son rang - Sud Ouest",
			"link": "https://www.sudouest.fr/sport/sports-de-combat-a-saintes-le-champion-du-monde-figuereido-landman-a-assume-son-rang-24863488.php",
			"pubDate": "Sun, 15 Jun 2025 18:34:16 GMT",
			"image": "https://media.sudouest.fr/24863488/1200x-1/20250615114524-nuitdelimpact252.jpg",
			"logo": "https://picsum.photos/32/32?grayscale",
			"site_name": "SudOuest.fr",
			"url": "https://www.sudouest.fr/sport/sports-de-combat-a-saintes-le-champion-du-monde-figuereido-landman-a-assume-son-rang-24863488.php",
			"description": "Le champion du monde a remport\u00e9 haut la main son combat disput\u00e9 face au champion d\u2019Europe Ilyass Chakir, samedi 14 juin \u00e0 Saintes, lors de la Nuit de l\u2019Impact"
		},
		{
			"title": "TOULON : CDOS - Cl\u00f4ture du dispositif RE'Action Sport Sant\u00e9 - Presse Agence",
			"link": "https://presseagence.fr/toulon-cdos-cloture-du-dispositif-reaction-sport-sante/",
			"pubDate": "Sun, 15 Jun 2025 17:00:00 GMT",
			"image": "https://presseagence.fr/wp-content/uploads/image-3595.jpeg",
			"logo": "https://picsum.photos/32/32?grayscale",
			"site_name": "Presse Agence",
			"url": "https://presseagence.fr/toulon-cdos-cloture-du-dispositif-reaction-sport-sante/",
			"description": "Le dispositif \u00ab\u00a0RE\u2019Action Sport Sant\u00e9\u00a0\u00bb c\u00e9l\u00e8bre sa cl\u00f4ture \u00e0 Toulon. Le Comit\u00e9 D\u00e9partemental Olympique et Sportif du Var organise une s\u00e9ance de cl\u00f4ture pour le dispositif \u00ab RE\u2019Action Sport Sant\u00e9 \u00bb le lundi 16 juin \u00e0 17h \u00e0 l\u2019\u00e9cole \u00e9l\u00e9mentaire Beaucaire. Ce programme, mis en place dans le cadre des \u00ab Cit\u00e9s \u00e9ducatives \u00bb, vise [\u2026]"
		},
		{
			"title": "Nico Williams au Bar\u00e7a si\u2026 - Sport.fr",
			"link": "https://www.sport.fr/football/nico-williams-au-barca-si-1354725.shtm",
			"pubDate": "Sun, 15 Jun 2025 17:32:22 GMT",
			"image": "https://www.sport.fr/wp-content/uploads/2025/05/ICONSPORT_258412_0006-2.jpg",
			"logo": "https://picsum.photos/32/32?grayscale",
			"site_name": "Sport.fr",
			"url": "https://www.sport.fr/football/nico-williams-au-barca-si-1354725.shtm",
			"description": "Le feuilleton Nico Williams refait surface en Catalogne. Selon Mundo Deportivo, le FC Barcelone r\u00eave toujours de faire venir l'ailier espagnol de 22 ans, mais plusieurs conditions restent \u00e0 remplir avant de l\u2019imaginer en Blaugrana aux c\u00f4t\u00e9s de Pedri et Lamine Yamal.\u00a0 Bien que le joueur privil\u00e9gierait le Bar\u00e7a \u2014\u2026"
		},
		{
			"title": "Sport boules \u2013 G\u00e9nelard bat tous les cadors et s\u2019impose sur ses terres - L'infoRmateur de Bourgogne",
			"link": "https://linformateurdebourgogne.com/sport-boules-genelard-bat-tous-les-cadors-et-simpose-sur-ses-terres/",
			"pubDate": "Sun, 15 Jun 2025 04:01:15 GMT",
			"image": "https://linformateurdebourgogne.com/wp-content/uploads/2025/06/genelard-boules.jpg",
			"logo": "https://picsum.photos/32/32?grayscale",
			"site_name": "L'infoRmateur de Bourgogne",
			"url": "https://linformateurdebourgogne.com/sport-boules-genelard-bat-tous-les-cadors-et-simpose-sur-ses-terres/",
			"description": "G\u00e9nelard imp\u00e9rial \u00e0 domicile et monte sur le podium au classement g\u00e9n\u00e9ral de la ligue M1. La formation de G\u00e9nelard a remport\u00e9 ce samedi 14 juin la 9e et avant-derni\u00e8re \u00e9tape de la Ligue M1 disput\u00e9e \u00e0 domicile. Emmen\u00e9e par un Anthony Percherancier des grands jours, l\u2019\u00e9quipe de Sa\u00f4ne-et-Loire a\u2026 Suite..."
		},
		{
			"title": "[Sport E.Leclerc Acad\u00e9mie] Le bilan de fin de saison d\u2019Anthony Morele - FC Gueugnon",
			"link": "https://www.fcgueugnon.fr/site/sport-e-leclerc-academie-le-bilan-de-fin-de-saison-danthony-morele/54572",
			"pubDate": "Sun, 15 Jun 2025 09:30:00 GMT",
			"image": "https://www.fcgueugnon.fr/site/wp-content/uploads/2025/06/Visuel-Anthony.jpg",
			"logo": "https://picsum.photos/32/32?grayscale",
			"site_name": "FOOTBALL CLUB GUEUGNON",
			"url": "https://www.fcgueugnon.fr/site/sport-e-leclerc-academie-le-bilan-de-fin-de-saison-danthony-morele/54572",
			"description": "C\u2019est cette fois le tour d\u2019Anthony Morele, entra\u00eeneur des U18, de dresser le bilan de la saison \u00e9coul\u00e9e et d\u2019aborder les perspectives pour 2025/2026. Cat\u00e9gorie U18 \u2013 Anthony MORELE(2\u00e8me : 16V, 2N, 4D) Peux-tu te pr\u00e9senter, ainsi que ta cat\u00e9gorie ?Je m\u2019appelle Anthony Morele, j\u2019ai 28 ans. Je suis de retour au FC Gueugnon depuis ... Lire la suite"
		},
		{
			"title": "Veauche. L\u2019office des sports propose un apr\u00e8s-midi de jeux d\u2019\u00e9t\u00e9 - Le Progr\u00e8s",
			"link": "https://www.leprogres.fr/sport/2025/06/15/l-office-des-sports-propose-un-apres-midi-de-jeux-d-ete",
			"pubDate": "Sun, 15 Jun 2025 17:22:40 GMT",
			"image": "https://cdn-s-www.leprogres.fr/images/74585A73-A3BE-4F67-9A5D-4773B5E37F05/FB1200/photo-1750007887.jpg",
			"logo": "https://picsum.photos/32/32?grayscale",
			"site_name": "",
			"url": "https://www.leprogres.fr/sport/2025/06/15/l-office-des-sports-propose-un-apres-midi-de-jeux-d-ete",
			"description": "En janvier\u00a02024, le bureau de l\u2019office des sports s\u2019est dot\u00e9 d\u2019une nouvelle \u00e9quipe. Les responsables ont renforc\u00e9 les liens avec les associations ..."
		},
		{
			"title": "OL : Une offre XXL pour Thiago Almada - Sport.fr",
			"link": "https://www.sport.fr/football/ol-une-offre-xxl-pour-thiago-almada-1354743.shtm",
			"pubDate": "Sun, 15 Jun 2025 18:32:00 GMT",
			"image": "https://www.sport.fr/wp-content/uploads/2025/03/ICONSPORT_252439_0315.jpg",
			"logo": "https://picsum.photos/32/32?grayscale",
			"site_name": "Sport.fr",
			"url": "https://www.sport.fr/football/ol-une-offre-xxl-pour-thiago-almada-1354743.shtm",
			"description": "Apr\u00e8s six mois prometteurs sous les couleurs de l\u2019OL, Thiago Almada se retrouve dans une situation complexe.\u00a0 Pr\u00eat\u00e9 par Botafogo, le meneur argentin ne verra pas l\u2019option d\u2019achat de plus de 20 millions d\u2019euros lev\u00e9e par Lyon. Officiellement, il doit retourner au club br\u00e9silien, mais il ne jouera ni la\u2026"
		},
		{
			"title": "Realteam Spirit s'impose 13 ans apr\u00e8s - rts.ch",
			"link": "https://www.rts.ch/sport/2025/article/realteam-spirit-s-impose-13-ans-apres-28915372.html",
			"pubDate": "Sun, 15 Jun 2025 20:12:05 GMT",
			"image": "https://img.rts.ch/articles/2025/image/ksjdsd-28915370.image?w=1200&h=630",
			"logo": "https://picsum.photos/32/32?grayscale",
			"site_name": "RTSSport.ch",
			"url": "https://www.rts.ch/sport/2025/article/realteam-spirit-s-impose-13-ans-apres-28915372.html",
			"description": "Treize ans apr\u00e8s sa premi\u00e8re victoire, Realteam Spirit a remport\u00e9 un nouveau Bol d'Or. Le multicoque d\u2019Esteban Garcia, skipp\u00e9 par J\u00e9r\u00f4me Clerc, s'est impos\u00e9 en 15h26'05."
		},
		{
			"title": "Mercato fou \u00e0 Nantes, l\u2019AS Monaco s\u2019en m\u00eale - Sport.fr",
			"link": "https://www.sport.fr/football/mercato-fou-a-nantes-las-monaco-sen-mele-1354650.shtm",
			"pubDate": "Sun, 15 Jun 2025 17:02:00 GMT",
			"image": "https://www.sport.fr/wp-content/uploads/2025/03/ICONSPORT_253048_0449.jpg",
			"logo": "https://picsum.photos/32/32?grayscale",
			"site_name": "Sport.fr",
			"url": "https://www.sport.fr/football/mercato-fou-a-nantes-las-monaco-sen-mele-1354650.shtm",
			"description": "Le mercato estival s\u2019emballe autour des jeunes talents du FC Nantes. Apr\u00e8s Nathan Z\u00e9z\u00e9 et Matthis Abline, c\u2019est d\u00e9sormais Louis Leroux, lat\u00e9ral gauche de 19 ans, qui suscite l\u2019int\u00e9r\u00eat de plusieurs clubs, dont l\u2019AS Monaco. Malgr\u00e9 une saison difficile pour Nantes, la formation continue d\u2019exporter de belles promesses. Selon L\u2019\u00c9quipe,\u2026"
		},
		{
			"title": "OL : 6 millions, un milieu low-cost fait r\u00eaver Lyon - Sport.fr",
			"link": "https://www.sport.fr/football/ol-6-millions-un-milieu-low-cost-fait-rever-lyon-1354647.shtm",
			"pubDate": "Sun, 15 Jun 2025 16:32:00 GMT",
			"image": "https://www.sport.fr/wp-content/uploads/2025/05/ICONSPORT_258202_0128-1.jpg",
			"logo": "https://picsum.photos/32/32?grayscale",
			"site_name": "Sport.fr",
			"url": "https://www.sport.fr/football/ol-6-millions-un-milieu-low-cost-fait-rever-lyon-1354647.shtm",
			"description": "L\u2019Olympique Lyonnais pr\u00e9pare un mercato serr\u00e9 pour l\u2019\u00e9t\u00e9 2025, contraint par une possible restriction financi\u00e8re d\u00e9cid\u00e9e par la DNCG.\u00a0 Dans ce contexte, le club cherche des talents accessibles, et le nom de Maxi Oyedele revient avec insistance. Ce jeune milieu d\u00e9fensif polonais de 20 ans \u00e9volue actuellement au Legia Varsovie,\u2026"
		},
		{
			"title": "A Mayotte, le cyclone Chido a aussi sinistr\u00e9 des sports comme le handball - Outre-mer la 1\u00e8re",
			"link": "https://la1ere.franceinfo.fr/mayotte/a-mayotte-le-cyclone-chido-a-aussi-sinistre-des-sports-comme-le-handball-1595814.html",
			"pubDate": "Sun, 15 Jun 2025 14:16:20 GMT",
			"image": "/image/KwAWABOSLQk82UYlm4QYRNYmaE8/930x620/outremer/2025/06/15/reprisesport-720-684ed0b26318c686476253.jpg",
			"logo": "https://picsum.photos/32/32?grayscale",
			"site_name": "Mayotte la 1\u00e8re",
			"url": "https://la1ere.franceinfo.fr/mayotte/a-mayotte-le-cyclone-chido-a-aussi-sinistre-des-sports-comme-le-handball-1595814.html",
			"description": "Comment reprendre le championnat lorsque les plateaux sportifs endommag\u00e9s par le passage de Chido n'ont pas b\u00e9n\u00e9fici\u00e9 de r\u00e9parations ? C'est la question qui se pose notamment dans le handball mahorais. Beaucoup d'infrastructures attendent toujours l'intervention des mairies. Le basket-ball local lui, semble mieux s'en sortir."
		},
		{
			"title": "Lison Jalby : jeune talent prometteur au tir au pistolet \u00e0 Saint-Ju\u00e9ry - ladepeche.fr",
			"link": "https://www.ladepeche.fr/2025/06/15/lison-jalby-jeune-talent-prometteur-au-tir-au-pistolet-a-saint-juery-12760107.php",
			"pubDate": "Sun, 15 Jun 2025 09:31:00 GMT",
			"image": "https://images.ladepeche.fr/api/v1/images/view/684c25636be2464452059434/large/image.jpg?v=1",
			"logo": "https://picsum.photos/32/32?grayscale",
			"site_name": "ladepeche.fr",
			"url": "https://www.ladepeche.fr/2025/06/15/lison-jalby-jeune-talent-prometteur-au-tir-au-pistolet-a-saint-juery-12760107.php",
			"description": "Avec seulement une ann\u00e9e de pratique, elle s\u2019impose dans une discipline exigeante et m\u00e9connue, le tir au pistolet."
		},
		{
			"title": "70 millions, Mora dit oui au PSG ! - Sport.fr",
			"link": "https://www.sport.fr/football/70-millions-mora-dit-oui-au-psg-1354656.shtm",
			"pubDate": "Sun, 15 Jun 2025 16:16:45 GMT",
			"image": "https://www.sport.fr/wp-content/uploads/2025/04/ICONSPORT_253199_0051-2.jpg",
			"logo": "https://picsum.photos/32/32?grayscale",
			"site_name": "Sport.fr",
			"url": "https://www.sport.fr/football/70-millions-mora-dit-oui-au-psg-1354656.shtm",
			"description": "Le Paris Saint-Germain ne rel\u00e2che pas la pression sur le dossier Rodrigo Mora. Le jeune milieu offensif de 18 ans du FC Porto se rapproche de plus en plus de la capitale fran\u00e7aise, malgr\u00e9 une clause lib\u00e9ratoire r\u00e9cemment fix\u00e9e \u00e0 70 millions d\u2019euros par le club portugais. Selon les informations\u2026"
		},
		{
			"title": "La F\u00eate du Sport - sports.gouv.fr",
			"link": "https://www.sports.gouv.fr/la-fete-du-sport-9836",
			"pubDate": "Thu, 05 Jun 2025 07:00:00 GMT",
			"image": "https://picsum.photos/200/300?grayscale",
			"logo": "https://picsum.photos/32/32?grayscale",
			"site_name": "",
			"url": "",
			"description": ""
		},
		{
			"title": "CdM des clubs : Bayern \u00e9clate Auckland City 10-0 - Sport.fr",
			"link": "https://www.sport.fr/football/cdm-des-clubs-bayern-eclate-auckland-city-10-0-1354076.shtm",
			"pubDate": "Sun, 15 Jun 2025 18:03:20 GMT",
			"image": "https://www.sport.fr/wp-content/uploads/2025/06/ICONSPORT_260375_0056.jpg",
			"logo": "https://picsum.photos/32/32?grayscale",
			"site_name": "Sport.fr",
			"url": "https://www.sport.fr/football/cdm-des-clubs-bayern-eclate-auckland-city-10-0-1354076.shtm",
			"description": "Le Bayern Munich a \u00e9cras\u00e9 Auckland City 10-0, dimanche, avec des Fran\u00e7ais en feu. Coman, Boey et Olise ont marqu\u00e9, tandis que M\u00fcller et Musiala ont sign\u00e9 un tripl\u00e9. Une d\u00e9monstration totale dans ce groupe C tr\u00e8s relev\u00e9. Acc\u00e8s au direct https://twitter.com/FCBayernEN"
		},
		{
			"title": "Quand Cristiano Ronaldo s\u2019affiche \u00e0 la salle de sport avec son fils - Foot Mercato",
			"link": "https://www.footmercato.net/a8181971698962180705-quand-cristiano-ronaldo-saffiche-a-la-salle-de-sport-avec-son-fils",
			"pubDate": "Sun, 15 Jun 2025 14:09:18 GMT",
			"image": "https://assets-fr.imgfoot.com/media/cache/1200x675/cr7-68467a768d83e.jpg",
			"logo": "https://picsum.photos/32/32?grayscale",
			"site_name": "Foot Mercato : Info Transferts Football - Actu Foot Transfert",
			"url": "https://www.footmercato.net/a8181971698962180705-quand-cristiano-ronaldo-saffiche-a-la-salle-de-sport-avec-son-fils",
			"description": "Cristiano Ronaldo a s\u00fbrement l\u2019une des plus belles carri\u00e8res de l\u2019histoire du football. Passant par un nombre incalculable d\u2019\u00e9preuves, le Portuga (...) - Footmercato"
		},
		{
			"title": "Manchester United : Un club va vendre sa section f\u00e9minine pour Rashford ! - Sport.fr",
			"link": "https://www.sport.fr/football/manchester-united-un-club-va-vendre-sa-section-feminine-pour-rashford-1354642.shtm",
			"pubDate": "Sun, 15 Jun 2025 16:02:00 GMT",
			"image": "https://www.sport.fr/wp-content/uploads/2025/05/ICONSPORT_257796_0033-1.jpg",
			"logo": "https://picsum.photos/32/32?grayscale",
			"site_name": "Sport.fr",
			"url": "https://www.sport.fr/football/manchester-united-un-club-va-vendre-sa-section-feminine-pour-rashford-1354642.shtm",
			"description": "Marcus Rashford agite d\u00e9j\u00e0 le mercato estival, et l\u2019Angleterre se passionne pour le futur de l\u2019attaquant de Manchester United.\u00a0 Si l\u2019international anglais r\u00eave toujours de rejoindre le FC Barcelone, son avenir pourrait bien s\u2019\u00e9crire du c\u00f4t\u00e9 d\u2019Aston Villa, o\u00f9 il a brill\u00e9 en pr\u00eat cette saison. Reste un obstacle :\u2026"
		},
		{
			"title": "Aix-les-Bains - Passion automobile lors du rassemblement Renault Sport et Alpine - Savoie News",
			"link": "https://www.savoie-news.fr/reportages/auto-moto/article/passion-automobile-lors-du-rassemblement-renault-sport-et-alpine",
			"pubDate": "Sun, 15 Jun 2025 07:00:00 GMT",
			"image": "https://www.savoie-news.fr/uploads/11682-684c600337e5f-s1-jpg.jpg",
			"logo": "https://picsum.photos/32/32?grayscale",
			"site_name": "Savoie News",
			"url": "https://www.savoie-news.fr/reportages/auto-moto/article/passion-automobile-lors-du-rassemblement-renault-sport-et-alpine",
			"description": " La 13e \u00e9dition du rassemblement Renault Sport et Alpine a r\u00e9uni 170 \u00e9quipages venus partager leur passion autour de v\u00e9hicules embl\u00e9matiques. O..."
		},
		{
			"title": "En 1928, la Tracta D2 Sport arriva, et ne s'imposa pas - Caradisiac",
			"link": "https://www.caradisiac.com/en-1928-la-tracta-d2-sport-arriva-et-ne-s-imposa-pas-216250.htm",
			"pubDate": "Sun, 15 Jun 2025 05:00:00 GMT",
			"image": "https://images.caradisiac.com/logos/9/1/5/7/289157/S8-en-1928-la-tracta-d2-sport-arriva-et-ne-s-imposa-pas-216250.jpg",
			"logo": "https://picsum.photos/32/32?grayscale",
			"site_name": "Caradisiac.com",
			"url": "https://www.caradisiac.com/en-1928-la-tracta-d2-sport-arriva-et-ne-s-imposa-pas-216250.htm",
			"description": "LES VOITURES LES PLUS RAPIDES DU MONDE - Aux 24\u00a0heures du\u00a0Mans 1928 s'aligne un ovni de 60 ch capable d'atteindre 128\u00a0km / h.\u00a0C'est une Tracta, une traction avant sign\u00e9e Jean Albert Gr\u00e9goire. Encore une oubli\u00e9e de l'histoire."
		},
		{
			"title": "C\u2019est fait, le PSG va l\u00e2cher 60 M\u20ac pour\u2026 - Sport.fr",
			"link": "https://www.sport.fr/football/cest-fait-le-psg-va-lacher-60-me-pour-1354655.shtm",
			"pubDate": "Sun, 15 Jun 2025 15:15:00 GMT",
			"image": "https://www.sport.fr/wp-content/uploads/2025/03/ICONSPORT_247635_0005.jpg",
			"logo": "https://picsum.photos/32/32?grayscale",
			"site_name": "Sport.fr",
			"url": "https://www.sport.fr/football/cest-fait-le-psg-va-lacher-60-me-pour-1354655.shtm",
			"description": "Le Paris Saint-Germain s\u2019appr\u00eate \u00e0 frapper fort sur le march\u00e9 des transferts.\u00a0 D\u2019apr\u00e8s les informations du journaliste Matteo Moretto, un accord est imminent avec Bournemouth pour le transfert du d\u00e9fenseur central ukrainien Ilya Zabarnyi. Un renfort majeur voulu par Luis Enrique pour densifier son arri\u00e8re-garde. Une d\u00e9fense renforc\u00e9e pour Luis\u2026"
		},
		{
			"title": "Bar\u00e7a : Les 4 dossier ultra brulants de Deco - Sport.fr",
			"link": "https://www.sport.fr/football/barca-les-4-dossier-ultra-brulants-de-deco-1354610.shtm",
			"pubDate": "Sun, 15 Jun 2025 15:04:14 GMT",
			"image": "https://www.sport.fr/wp-content/uploads/2022/06/Icon_ACP_140318_45_44-1.jpg",
			"logo": "https://picsum.photos/32/32?grayscale",
			"site_name": "Sport.fr",
			"url": "https://www.sport.fr/football/barca-les-4-dossier-ultra-brulants-de-deco-1354610.shtm",
			"description": "Le FC Barcelone, port\u00e9 par ses r\u00e9cents succ\u00e8s en Liga et sa demi-finale de Ligue des Champions, entend frapper fort lors du mercato estival, malgr\u00e9 des finances contraintes.\u00a0 Pour mener \u00e0 bien ses ambitions, Deco, le directeur sportif, doit pourtant r\u00e9gler quatre dossiers \u00e9pineux, tous li\u00e9s \u00e0 des joueurs dont\u2026"
		},
		{
			"title": "OL : Ce joueur perd patience et va d\u00e9finitivement tourner la page - Sport.fr",
			"link": "https://www.sport.fr/football/ol-ce-joueur-perd-patience-et-va-definitivement-tourner-la-page-1354602.shtm",
			"pubDate": "Sun, 15 Jun 2025 14:32:00 GMT",
			"image": "https://www.sport.fr/wp-content/uploads/2024/07/ICONSPORT_130670_0026.jpg",
			"logo": "https://picsum.photos/32/32?grayscale",
			"site_name": "Sport.fr",
			"url": "https://www.sport.fr/football/ol-ce-joueur-perd-patience-et-va-definitivement-tourner-la-page-1354602.shtm",
			"description": "Avec l\u2019arriv\u00e9e imminente du gardien am\u00e9ricain Matt Turner, l\u2019Olympique Lyonnais semble pr\u00e9parer un bouleversement dans son poste de num\u00e9ro 2.\u00a0 R\u00e9my Descamps, actuel doublure ayant disput\u00e9 seulement trois matchs cette saison, commence \u00e0 perdre patience et souhaite d\u00e9sormais plus de temps de jeu. Son agent, Christophe Mongai, a confirm\u00e9 cette\u2026"
		},
		{
			"title": "PARIS : Renouvellement du partenariat avec la Fondation du Sport Fran\u00e7ais - Presse Agence",
			"link": "https://presseagence.fr/paris-renouvellement-du-partenariat-avec-la-fondation-du-sport-francais/",
			"pubDate": "Sun, 15 Jun 2025 11:00:00 GMT",
			"image": "https://presseagence.fr/wp-content/uploads/image-3538.jpeg",
			"logo": "https://picsum.photos/32/32?grayscale",
			"site_name": "Presse Agence",
			"url": "https://presseagence.fr/paris-renouvellement-du-partenariat-avec-la-fondation-du-sport-francais/",
			"description": "Ceetrus renouvelle son engagement aupr\u00e8s de la Fondation du Sport Fran\u00e7ais avec un investissement significatif. Ceetrus, acteur majeur de l\u2019immobilier commercial, a r\u00e9cemment renouvel\u00e9 son partenariat avec la Fondation du Sport Fran\u00e7ais (FSF). Ce m\u00e9c\u00e9nat, d\u2019un montant de 1,25 million d\u2019euros, a \u00e9t\u00e9 r\u00e9compens\u00e9 par le troph\u00e9e \u00ab Initiatives locales / Marketing \u00bb lors du [\u2026]"
		},
		{
			"title": "OL : Un v\u00e9ritable miracle se produit pour Textor - Sport.fr",
			"link": "https://www.sport.fr/football/ol-un-veritable-miracle-se-produit-pour-textor-1354639.shtm",
			"pubDate": "Sun, 15 Jun 2025 15:32:00 GMT",
			"image": "https://www.sport.fr/wp-content/uploads/2024/07/ICONSPORT_221756_0020.jpg",
			"logo": "https://picsum.photos/32/32?grayscale",
			"site_name": "Sport.fr",
			"url": "https://www.sport.fr/football/ol-un-veritable-miracle-se-produit-pour-textor-1354639.shtm",
			"description": "Pr\u00eat\u00e9 cette saison \u00e0 Everton, Orel Mangala a connu un coup dur en janvier dernier en se blessant gravement au genou. L\u2019Olympique Lyonnais, propri\u00e9taire du joueur depuis l\u2019hiver 2024, a rapidement d\u00fb g\u00e9rer la situation apr\u00e8s la rupture du ligament crois\u00e9 ant\u00e9rieur de son milieu d\u00e9fensif belge. Everton a mis\u2026"
		},
		{
			"title": "Jubil\u00e9 du sport: des champions, mais surtout des artisans de l'esp\u00e9rance - Vatican News",
			"link": "https://www.vaticannews.va/fr/vatican/news/2025-06/jubile-sport-conference-de-presse-saint-siege.html",
			"pubDate": "Wed, 11 Jun 2025 16:34:20 GMT",
			"image": "https://www.vaticannews.va/content/dam/vaticannews/multimedia/2025/giugno/11/WhatsApp-Image-2025-06-11-at-14.31.24.jpg/_jcr_content/renditions/cq5dam.thumbnail.cropped.1500.844.jpeg",
			"logo": "https://picsum.photos/32/32?grayscale",
			"site_name": "",
			"url": "https://www.vaticannews.va/fr/vatican/news/2025-06/jubile-sport-conference-de-presse-saint-siege.html",
			"description": "Ce mercredi, les \u00e9v\u00e9nements pr\u00e9vus les 14 et 15 juin \u00e0 l'occasion du Jubil\u00e9 du sport ont \u00e9t\u00e9 pr\u00e9sent\u00e9s en Salle de presse du Saint-Si\u00e8ge. Une ..."
		},
		{
			"title": "VID\u00c9O \u2013 Rugby \u2013 L\u2019US Millas qualifi\u00e9e en demi-finale de R\u00e9gionale 1 - L'Ind\u00e9pendant",
			"link": "https://www.lindependant.fr/2025/06/15/video-rugby-lus-millas-qualifiee-en-demi-finale-de-regionale-1-12763710.php",
			"pubDate": "Sun, 15 Jun 2025 15:31:00 GMT",
			"image": "https://images.lindependant.fr/api/v1/images/view/684ee4d9c180eac1150733b4/large/image.jpg?v=1",
			"logo": "https://picsum.photos/32/32?grayscale",
			"site_name": "lindependant.fr",
			"url": "https://www.lindependant.fr/2025/06/15/video-rugby-lus-millas-qualifiee-en-demi-finale-de-regionale-1-12763710.php",
			"description": "Promue cette saison en R1, l\u2019US Millas s\u2019est qualifi\u00e9e ce dimanche du c\u00f4t\u00e9 de Castelnaudary en \u00e9liminant Pouyastruc 22-17). J\u00e9r\u00e9my Le Gal et les siens affronteront l\u2019Union Sportive Valr\u00e9assienne dimanche prochain,..."
		},
		{
			"title": "RUGBY : France A \u2013 La liste des joueurs convoqu\u00e9s - Presse Agence Sport",
			"link": "http://www.pa-sport.fr/2025/06/15/rugby-france-a-la-liste-des-joueurs-convoques/",
			"pubDate": "Sun, 15 Jun 2025 16:10:03 GMT",
			"image": "http://www.pa-sport.fr/wp-content/uploads/image-326.jpeg",
			"logo": "https://picsum.photos/32/32?grayscale",
			"site_name": "Presse Agence Sport",
			"url": "https://www.pa-sport.fr/2025/06/15/rugby-france-a-la-liste-des-joueurs-convoques/",
			"description": "La F\u00e9d\u00e9ration Fran\u00e7aise de Rugby d\u00e9voile la liste des joueurs convoqu\u00e9s pour le match contre l\u2019Angleterre XV. La F\u00e9d\u00e9ration Fran\u00e7aise de Rugby (FFR) a annonc\u00e9 la liste des joueurs convoqu\u00e9s dans le groupe France A pour la pr\u00e9paration du match face \u00e0 l\u2019Angleterre XV. Ce match, pr\u00e9vu pour le samedi 21 juin \u00e0 16h15 \u00e0 [\u2026]"
		},
		{
			"title": "Manchester City s\u2019offre une sacr\u00e9 p\u00e9pite du PSG ! - Sport.fr",
			"link": "https://www.sport.fr/football/manchester-city-soffre-une-sacre-pepite-du-psg-1354592.shtm",
			"pubDate": "Sun, 15 Jun 2025 13:14:40 GMT",
			"image": "https://www.sport.fr/wp-content/uploads/2023/02/Icon_38296778.jpg",
			"logo": "https://picsum.photos/32/32?grayscale",
			"site_name": "Sport.fr",
			"url": "https://www.sport.fr/football/manchester-city-soffre-une-sacre-pepite-du-psg-1354592.shtm",
			"description": "Le jeune attaquant Mahamadou Sangar\u00e9, 18 ans, va quitter le Paris Saint-Germain pour rejoindre Manchester City. Selon RMC Sport, le joueur a pass\u00e9 sa visite m\u00e9dicale avec les Citizens ce vendredi et s\u2019est engag\u00e9 pour un contrat de cinq ans, jusqu\u2019en 2030. Sangar\u00e9, meilleur buteur de la Youth League cette\u2026"
		},
		{
			"title": "Prix de Diane : Parker, Griezmann, Ancelotti\u2026 Ces stars du sport propri\u00e9taires de chevaux entra\u00een\u00e9s \u00e0 Chantilly - Le Parisien",
			"link": "https://www.leparisien.fr/oise-60/prix-de-diane-parker-griezmann-ancelotti-ces-stars-du-sport-proprietaires-de-chevaux-entraines-a-chantilly-15-06-2025-QITHRVW5HBEHZELCXCTIEC2KJI.php",
			"pubDate": "Sun, 15 Jun 2025 05:02:00 GMT",
			"image": "https://www.leparisien.fr/resizer/7qTI0Sgde-xB641P_K_Cp2EwlCA=/1200x675/cloudfront-eu-central-1.images.arcpublishing.com/leparisien/IOJAS72HXVH7XEYNTSFNYI5NHE.jpg",
			"logo": "https://picsum.photos/32/32?grayscale",
			"site_name": "leparisien.fr",
			"url": "https://www.leparisien.fr/oise-60/prix-de-diane-parker-griezmann-ancelotti-ces-stars-du-sport-proprietaires-de-chevaux-entraines-a-chantilly-15-06-2025-QITHRVW5HBEHZELCXCTIEC2KJI.php",
			"description": "Depuis plusieurs ann\u00e9es, les stars du sport propri\u00e9taires de chevaux de course pl\u00e9biscitent les entra\u00eeneurs de Chantilly (Oise), ville qui c"
		},
		{
			"title": "Crit\u00e9rium du Dauphin\u00e9. Quand les coureurs essaient un sport in\u00e9dit avec plus ou moins de r\u00e9ussite - Ouest-France",
			"link": "https://www.ouest-france.fr/sport/cyclisme/criterium-du-dauphine/criterium-du-dauphine-quand-les-coureurs-essaient-un-sport-inedit-avec-plus-ou-moins-de-reussite-0fedc6d8-49b4-11f0-9d37-5ecd6f11d520",
			"pubDate": "Sun, 15 Jun 2025 07:19:14 GMT",
			"image": "",
			"logo": "https://picsum.photos/32/32?grayscale",
			"site_name": "",
			"url": "",
			"description": ""
		},
		{
			"title": "Un ancien de l\u2019OM ne jure que par l\u2019OL - Sport.fr",
			"link": "https://www.sport.fr/football/un-ancien-de-lom-ne-jure-que-par-lol-1354606.shtm",
			"pubDate": "Sun, 15 Jun 2025 14:45:00 GMT",
			"image": "https://www.sport.fr/wp-content/uploads/2023/05/Icon_FID_4682.jpg",
			"logo": "https://picsum.photos/32/32?grayscale",
			"site_name": "Sport.fr",
			"url": "https://www.sport.fr/football/un-ancien-de-lom-ne-jure-que-par-lol-1354606.shtm",
			"description": "L\u2019Olympique Lyonnais envisagerait de recruter Issa Kabor\u00e9 en pr\u00eat, un ancien joueur de l\u2019OM sous contrat avec Manchester City.\u00a0 Apr\u00e8s avoir c\u00e9d\u00e9 Rayan Cherki, Lyon maintient de bonnes relations avec le club anglais et pourrait ainsi accueillir un nouveau talent venu de l\u2019effectif des champions d\u2019Europe 2023. Un d\u00e9fenseur en\u2026"
		},
		{
			"title": "Force and fitness day, une journ\u00e9e 100% sport \u00e0 Noum\u00e9a pour d\u00e9couvrir la musculation - Outre-mer la 1\u00e8re",
			"link": "https://la1ere.franceinfo.fr/nouvellecaledonie/province-sud/noumea/force-and-fitness-day-une-journee-100-sport-a-noumea-pour-decouvrir-la-musculation-1595499.html",
			"pubDate": "Sat, 14 Jun 2025 09:54:07 GMT",
			"image": "/image/N_Jqlj10XGRbqpAsO_syFRJ2xLk/930x620/outremer/2025/06/14/img-0811-684d2e2817310425646795.jpg",
			"logo": "https://picsum.photos/32/32?grayscale",
			"site_name": "Nouvelle-Cal\u00e9donie la 1\u00e8re",
			"url": "https://la1ere.franceinfo.fr/nouvellecaledonie/province-sud/noumea/force-and-fitness-day-une-journee-100-sport-a-noumea-pour-decouvrir-la-musculation-1595499.html",
			"description": "Le comit\u00e9 r\u00e9gional des bodybuilders de Nouvelle-Cal\u00e9donie organisait samedi 14 juin une journ\u00e9e sportive au stade Numa Daly \u00e0 Magenta. L'objectif de la Force and fitness day \u00e9tait surtout de promouvoir la musculation, et l'activit\u00e9 physique \u00e0 travers des ateliers gratuits tout au long de la journ\u00e9e."
		},
		{
			"title": "Cyclisme. Tour f\u00e9minin international des Pyr\u00e9n\u00e9es \u2013 Troisi\u00e8me et derni\u00e8re \u00e9tape entre Abidos et Pau. en replay - France TV",
			"link": "https://www.france.tv/sport/7238858-cyclisme-tour-feminin-international-des-pyrenees-troisieme-et-derniere-etape-entre-abidos-et-pau.html",
			"pubDate": "Sun, 15 Jun 2025 17:10:15 GMT",
			"image": "https://medias.france.tv/S0ldPKe5WHv0s9t6xskYEdt42mw/880x0/filters:quality(85):format(jpeg)/c/y/d/phpt8xdyc.jpg",
			"logo": "https://picsum.photos/32/32?grayscale",
			"site_name": "",
			"url": "https://www.france.tv/sport/7238858-cyclisme-tour-feminin-international-des-pyrenees-troisieme-et-derniere-etape-entre-abidos-et-pau.html",
			"description": "Ultime \u00e9tape de ce tour qui r\u00e9unit parmi les meilleures du cyclisme f\u00e9minin. Cette quatri\u00e8me \u00e9dition compte 21 \u00e9quipes dont 4 du world Tour, le plus haut niv..."
		},
		{
			"title": "L\u2019OM se frotte \u00e0 Manchester United pour une p\u00e9pite s\u00e9n\u00e9galaise ! - Sport.fr",
			"link": "https://www.sport.fr/football/lom-se-frotte-a-manchester-united-pour-une-pepite-senegalaise-1354584.shtm",
			"pubDate": "Sun, 15 Jun 2025 12:44:00 GMT",
			"image": "https://www.sport.fr/wp-content/uploads/2024/07/ICONSPORT_220742_0239.jpg",
			"logo": "https://picsum.photos/32/32?grayscale",
			"site_name": "Sport.fr",
			"url": "https://www.sport.fr/football/lom-se-frotte-a-manchester-united-pour-une-pepite-senegalaise-1354584.shtm",
			"description": "L\u2019Olympique de Marseille vise un nouveau renfort d\u00e9fensif en ciblant Arouna Sangante, le jeune capitaine du Havre.\u00a0 \u00c0 seulement 23 ans, le S\u00e9n\u00e9galais arrive \u00e0 un an de la fin de son contrat, ce qui facilite son d\u00e9part. Mais l\u2019OM devra faire face \u00e0 une concurrence europ\u00e9enne redoutable. Une piste\u2026"
		},
		{
			"title": "\u00ab Entre backflip et raclette, d\u00e9couvrez Loli Bahia \u00bb, la mannequin fan de sport - L'\u00c9quipe",
			"link": "https://www.lequipe.fr/Tous-sports/Article/Grand-recit--entre-backflip-et-raclette-decouvrez-loli-bahia-la-mannequin-fan-de-sport/1569529",
			"pubDate": "Thu, 12 Jun 2025 15:00:00 GMT",
			"image": "https://medias.lequipe.fr/img-photo-jpg/sacha-balti-l-equipe/1500000002217880/0:0,612:306-1200-600-75/68414",
			"logo": "https://picsum.photos/32/32?grayscale",
			"site_name": "L'\u00c9quipe",
			"url": "https://www.lequipe.fr/Tous-sports/Article/Grand-recit--entre-backflip-et-raclette-decouvrez-loli-bahia-la-mannequin-fan-de-sport/1569529",
			"description": "Loli Bahia aime le ski, les Golden State Warriors et Carlos Alcaraz. Elle a fait du volley, des d\u00e9fil\u00e9s pour les plus grandes maisons de mode et des photos pour les plus grands magazines. Pour \u00ab\u00a0L'\u00c9quipe Magazine\u00a0\u00bb, la top model fran\u00e7aise la plus demand\u00e9e du moment a l\u00e2ch\u00e9 les studios pour un apr\u00e8s-midi de shooting \u00e0 l'Insep."
		},
		{
			"title": "Le tournoi de cricket des r\u00e9fugi\u00e9s remport\u00e9 par les Caennais . Sport - Maville",
			"link": "https://guingamp.maville.com/sport/infos/detail_-le-tournoi-de-cricket-des-refugies-remporte-par-les-caennais-_-6854815_actu.Htm",
			"pubDate": "Sun, 15 Jun 2025 17:00:00 GMT",
			"image": "https://maville.com/photosmvi/2025/06/15/P35292559D6854815G_crop_1080-600_.jpg",
			"logo": "https://picsum.photos/32/32?grayscale",
			"site_name": "",
			"url": "",
			"description": "Sport Guingamp Le tournoi de cricket des r\u00e9fugi\u00e9s remport\u00e9 par les Caennais - Sport national... Guingamp"
		},
		{
			"title": "Tottenham attaque en justice le propri\u00e9taire de l\u2019OGC Nice - Sport.fr",
			"link": "https://www.sport.fr/football/tottenham-attaque-en-justice-le-proprietaire-de-logc-nice-1354588.shtm",
			"pubDate": "Sun, 15 Jun 2025 13:02:00 GMT",
			"image": "https://www.sport.fr/wp-content/uploads/2024/06/ICONSPORT_223200_0149.jpg",
			"logo": "https://picsum.photos/32/32?grayscale",
			"site_name": "Sport.fr",
			"url": "https://www.sport.fr/football/tottenham-attaque-en-justice-le-proprietaire-de-logc-nice-1354588.shtm",
			"description": "Jim Ratcliffe, d\u00e9j\u00e0 fragilis\u00e9 financi\u00e8rement, voit la soci\u00e9t\u00e9 INEOS Automotive, qu\u2019il co-dirige, attaqu\u00e9e par Tottenham devant le tribunal de commerce de Londres.\u00a0 Selon Sky Sports, le club londonien reproche \u00e0 INEOS d\u2019avoir rompu pr\u00e9matur\u00e9ment un contrat de sponsoring sign\u00e9 en 2022, deux ans avant son terme pr\u00e9vu. Une rupture inattendue\u2026"
		},
		{
			"title": "\u00ab C'est agr\u00e9able de ne plus \u00eatre autant sous les projecteurs \u00bb : L'endurance, ce sport o\u00f9 l'\u00e9quipe prime sur le pilote - L'\u00c9quipe",
			"link": "https://www.lequipe.fr/Sport-auto/Article/-c-est-agreable-de-ne-plus-etre-autant-sous-les-projecteurs-l-endurance-ce-sport-ou-l-equipe-prime-sur-le-pilote/1570160",
			"pubDate": "Sun, 15 Jun 2025 04:30:00 GMT",
			"image": "https://medias.lequipe.fr/img-photo-jpg/kevin-magnussen-ancien-pilote-de-f1-ici-en-pleine-discussion-samedi-avec-son-equipier-raffaele-marciello-a-droite-chez-bmw-wrt-s-boue-l-equipe/1500000002219252/0:0,2000:1333-1200-800-75/333de",
			"logo": "https://picsum.photos/32/32?grayscale",
			"site_name": "L'\u00c9quipe",
			"url": "https://www.lequipe.fr/Sport-auto/Article/-c-est-agreable-de-ne-plus-etre-autant-sous-les-projecteurs-l-endurance-ce-sport-ou-l-equipe-prime-sur-le-pilote/1570160",
			"description": "Que ressent un pilote de F1, habitu\u00e9 \u00e0 \u00eatre au centre du monde, lorsqu'il rejoint une \u00e9quipe d'endurance\u00a0? La majorit\u00e9 semble appr\u00e9cier ce nouvel environnement."
		},
		{
			"title": "Armand Duplantis survole le ciel avec un nouveau record - Sport.fr",
			"link": "https://www.sport.fr/athletisme/armand-duplantis-survole-le-ciel-avec-un-nouveau-record-1354778.shtm",
			"pubDate": "Sun, 15 Jun 2025 20:07:10 GMT",
			"image": "https://www.sport.fr/wp-content/uploads/2024/08/ICONSPORT_236229_0046.jpg",
			"logo": "https://picsum.photos/32/32?grayscale",
			"site_name": "Sport.fr",
			"url": "https://www.sport.fr/athletisme/armand-duplantis-survole-le-ciel-avec-un-nouveau-record-1354778.shtm",
			"description": "Armand Duplantis a encore marqu\u00e9 l\u2019histoire du saut \u00e0 la perche en franchissant 6,28 m\u00e8tres d\u00e8s son premier essai, dimanche \u00e0 Stockholm. Cette performance exceptionnelle lui permet de battre pour la 12e fois son propre record du monde, d\u00e9montrant une fois de plus son incroyable ma\u00eetrise et son talent unique.\u2026"
		},
		{
			"title": "Judo : Joan-Benjamin Gaba sacr\u00e9 champion du monde en -73 kg - Sport.fr",
			"link": "https://www.sport.fr/judo/judo-joan-benjamin-gaba-sacre-champion-du-monde-en-73-kg-1354759.shtm",
			"pubDate": "Sun, 15 Jun 2025 17:59:03 GMT",
			"image": "https://www.sport.fr/wp-content/uploads/2024/07/ICONSPORT_235456_0115.jpg",
			"logo": "https://picsum.photos/32/32?grayscale",
			"site_name": "Sport.fr",
			"url": "https://www.sport.fr/judo/judo-joan-benjamin-gaba-sacre-champion-du-monde-en-73-kg-1354759.shtm",
			"description": "Joan-Benjamin Gaba a d\u00e9croch\u00e9 ce dimanche son tout premier titre mondial dans la cat\u00e9gorie des -73 kg lors des Championnats du monde \u00e0 Budapest. Le judoka fran\u00e7ais de 24 ans, d\u00e9j\u00e0 remarqu\u00e9 aux Jeux olympiques de Paris 2024, s\u2019est impos\u00e9 en finale face au Br\u00e9silien Daniel Cargnin au golden score,\u2026"
		},
		{
			"title": "Sport. Football : le Pays Ma\u00eechois de retour en R1, 23 ans apr\u00e8s ! - Hebdo25",
			"link": "https://hebdo25.net/foot-le-pays-maichois-en-r1/",
			"pubDate": "Sun, 15 Jun 2025 00:01:13 GMT",
			"image": "https://hebdo25.net/wp-content/uploads/2025/06/ESPM-R1.jpg",
			"logo": "https://picsum.photos/32/32?grayscale",
			"site_name": "Doubs : toute l'info locale - Hebdo25",
			"url": "https://hebdo25.net/foot-le-pays-maichois-en-r1/",
			"description": "Apr\u00e8s plus de 20 ans d\u2019attente, l\u2019Entente Sportive du Pays Ma\u00eechois, retrouve le plus haut niveau r\u00e9gional avec son \u00e9quipe fanion."
		},
		{
			"title": "Arsenal FC : 6 millions \u00e0 Chelsea pour\u2026 - Sport.fr",
			"link": "https://www.sport.fr/football/arsenal-fc-6-millions-a-chelsea-pour-1351621.shtm",
			"pubDate": "Sun, 15 Jun 2025 11:32:26 GMT",
			"image": "https://www.sport.fr/wp-content/uploads/2023/11/Icon_071_RMCRAY20231105_001-1.jpg",
			"logo": "https://picsum.photos/32/32?grayscale",
			"site_name": "Sport.fr",
			"url": "https://www.sport.fr/football/arsenal-fc-6-millions-a-chelsea-pour-1351621.shtm",
			"description": "Arsenal est sur le point d\u2019enregistrer l\u2019arriv\u00e9e de Kepa Arrizabalaga. \u00c0 30 ans, le gardien espagnol, pr\u00eat\u00e9 \u00e0 Bournemouth par Chelsea cette saison, va changer de camp \u00e0 Londres. Selon The Athletic, les Gunners vont lever sa clause lib\u00e9ratoire fix\u00e9e \u00e0 6 millions d\u2019euros. Malgr\u00e9 ses 31 matchs disput\u00e9s en\u2026"
		},
		{
			"title": "PSG : 10 millions d\u2019euros tomb\u00e9s du ciel ! - Sport.fr",
			"link": "https://www.sport.fr/football/psg-10-millions-deuros-tombes-du-ciel-1354550.shtm",
			"pubDate": "Sun, 15 Jun 2025 10:15:00 GMT",
			"image": "https://www.sport.fr/wp-content/uploads/2025/05/ICONSPORT_256140_0020.jpg",
			"logo": "https://picsum.photos/32/32?grayscale",
			"site_name": "Sport.fr",
			"url": "https://www.sport.fr/football/psg-10-millions-deuros-tombes-du-ciel-1354550.shtm",
			"description": "Alors que Fenerbah\u00e7e semblait tenir la corde, un retournement de situation est en train de se produire concernant l\u2019avenir de Milan Skriniar.\u00a0 Pr\u00eat\u00e9 cet hiver par le Paris Saint-Germain, le d\u00e9fenseur slovaque pourrait finalement rebondir chez le rival Galatasaray. Fenerbah\u00e7e d\u00e9pass\u00e9 dans la course Satisfait de ses performances depuis janvier,\u2026"
		},
		{
			"title": "FC Nantes : 20 millions d\u2019euros, Kita est un g\u00e9nie - Sport.fr",
			"link": "https://www.sport.fr/football/fc-nantes-20-millions-deuros-kita-est-un-genie-1348174.shtm",
			"pubDate": "Sun, 15 Jun 2025 09:03:40 GMT",
			"image": "https://www.sport.fr/wp-content/uploads/2025/05/ICONSPORT_260410_0077.jpg",
			"logo": "https://picsum.photos/32/32?grayscale",
			"site_name": "Sport.fr",
			"url": "https://www.sport.fr/football/fc-nantes-20-millions-deuros-kita-est-un-genie-1348174.shtm",
			"description": "Le FC Nantes s\u2019agite d\u00e9j\u00e0 sur le march\u00e9 des transferts. Selon Africa Foot, les Canaris souhaitent rapatrier Kamaldeen Sulemana, l\u2019ancien ailier du Stade Rennais aujourd\u2019hui en difficult\u00e9 \u00e0 Southampton. Un pari audacieux pour un joueur explosif mais frein\u00e9 par les blessures. R\u00e9v\u00e9l\u00e9 \u00e0 Rennes entre 2021 et 2023, Sulemana avait\u2026"
		},
		{
			"title": "Dou\u00e9 a dit oui \u00e0 l\u2019AC Milan ! - Sport.fr",
			"link": "https://www.sport.fr/football/doue-a-dit-oui-a-lac-milan-1354562.shtm",
			"pubDate": "Sun, 15 Jun 2025 11:02:30 GMT",
			"image": "https://www.sport.fr/wp-content/uploads/2023/11/Icon_sipausa_41978755.jpg",
			"logo": "https://picsum.photos/32/32?grayscale",
			"site_name": "Sport.fr",
			"url": "https://www.sport.fr/football/doue-a-dit-oui-a-lac-milan-1354562.shtm",
			"description": "Le RC Strasbourg s\u2019appr\u00eate \u00e0 perdre un de ses \u00e9l\u00e9ments les plus prometteurs.\u00a0 Gu\u00e9la Dou\u00e9, d\u00e9fenseur de 21 ans et pilier de la saison alsacienne, est dans le viseur de l\u2019AC Milan, selon les informations du m\u00e9dia Calcio Mercato. Les Rossoneri, en qu\u00eate de renforts d\u00e9fensifs pour entamer un nouveau\u2026"
		}
	],
	"timestamp": "2025-06-15 20:32:20.183133"
}